{
  "type": "Feature",
  "properties": {
    "gn:admin1_code":"00",
    "gn:asciiname":"Petit Marquisat",
    "gn:country_code":"GP",
    "gn:dem":292,
    "gn:feature_class":"P",
    "gn:feature_code":"PPL",
    "gn:name":"Petit Marquisat",
    "gn:population":0,
    "gn:timezone":"America/Guadeloupe",
    "iso:country":"GP",
    "name:fra_x_preferred":[
        "Petit Marquisat"
    ],
    "wof:name":"Petit Marquisat",
    "wof:placetype":"locality"
},
  "geometry": {"coordinates":[-61.60961999999999,16.04531],"type":"Point"}
}