{
  "type": "Feature",
  "properties": {
    "gn:admin1_code":"00",
    "gn:asciiname":"Bacoul",
    "gn:country_code":"GP",
    "gn:dem":147,
    "gn:feature_class":"P",
    "gn:feature_code":"PPL",
    "gn:name":"Bacoul",
    "gn:population":0,
    "gn:timezone":"America/Guadeloupe",
    "iso:country":"GP",
    "name:fra_x_preferred":[
        "Bacoul"
    ],
    "wof:name":"Bacoul",
    "wof:placetype":"locality"
},
  "geometry": {"coordinates":[-61.25881999999999,15.89434],"type":"Point"}
}