{
  "type": "Feature",
  "properties": {
    "gn:admin1_code":"00",
    "gn:asciiname":"Cantamerle",
    "gn:country_code":"GP",
    "gn:dem":168,
    "gn:feature_class":"P",
    "gn:feature_code":"PPL",
    "gn:name":"Cantamerle",
    "gn:population":0,
    "gn:timezone":"America/Guadeloupe",
    "iso:country":"GP",
    "name:fra_x_preferred":[
        "Cantamerle"
    ],
    "wof:name":"Cantamerle",
    "wof:placetype":"locality"
},
  "geometry": {"coordinates":[-61.59781,16.01865],"type":"Point"}
}