{
  "type": "Feature",
  "properties": {
    "gn:admin1_code":"00",
    "gn:asciiname":"Baret",
    "gn:country_code":"GP",
    "gn:dem":14,
    "gn:feature_class":"P",
    "gn:feature_code":"PPL",
    "gn:name":"Baret",
    "gn:population":0,
    "gn:timezone":"America/Guadeloupe",
    "iso:country":"GP",
    "name:fra_x_preferred":[
        "Baret"
    ],
    "wof:name":"Baret",
    "wof:placetype":"locality"
},
  "geometry": {"coordinates":[-61.6821,16.31542],"type":"Point"}
}