{
  "type": "Feature",
  "properties": {
    "gn:admin1_code":"00",
    "gn:asciiname":"Conodor",
    "gn:country_code":"GP",
    "gn:dem":28,
    "gn:feature_class":"P",
    "gn:feature_code":"PPL",
    "gn:name":"Conodor",
    "gn:population":0,
    "gn:timezone":"America/Guadeloupe",
    "iso:country":"GP",
    "name:fra_x_preferred":[
        "Conodor"
    ],
    "wof:name":"Conodor",
    "wof:placetype":"locality"
},
  "geometry": {"coordinates":[-61.67549,16.29021],"type":"Point"}
}