{
  "type": "Feature",
  "properties": {
    "gn:admin1_code":"00",
    "gn:asciiname":"Saint-Louis",
    "gn:country_code":"GP",
    "gn:dem":389,
    "gn:feature_class":"P",
    "gn:feature_code":"PPL",
    "gn:name":"Saint-Louis",
    "gn:population":0,
    "gn:timezone":"America/Guadeloupe",
    "iso:country":"GP",
    "name:fra_x_preferred":[
        "Saint-Louis"
    ],
    "wof:name":"Saint-Louis",
    "wof:placetype":"locality"
},
  "geometry": {"coordinates":[-61.71554,16.03315],"type":"Point"}
}