{
  "type": "Feature",
  "properties": {
    "gn:admin1_code":"00",
    "gn:asciiname":"Concessions",
    "gn:country_code":"GP",
    "gn:dem":355,
    "gn:feature_class":"P",
    "gn:feature_code":"PPLL",
    "gn:name":"Concessions",
    "gn:population":0,
    "gn:timezone":"America/Guadeloupe",
    "iso:country":"GP",
    "name:fra_x_preferred":[
        "Concessions"
    ],
    "wof:name":"Concessions",
    "wof:placetype":"locality"
},
  "geometry": {"coordinates":[-61.6171,16.05377],"type":"Point"}
}