{
  "type": "Feature",
  "properties": {
    "gn:admin1_code":"00",
    "gn:asciiname":"Celigny",
    "gn:country_code":"GP",
    "gn:dem":65,
    "gn:feature_class":"P",
    "gn:feature_code":"PPL",
    "gn:name":"C\u00e9ligny",
    "gn:population":0,
    "gn:timezone":"America/Guadeloupe",
    "iso:country":"GP",
    "name:fra_x_preferred":[
        "C\u00e9ligny"
    ],
    "wof:name":"Celigny",
    "wof:placetype":"locality"
},
  "geometry": {"coordinates":[-61.46448,16.26452],"type":"Point"}
}