{
  "type": "Feature",
  "properties": {
    "gn:admin1_code":"00",
    "gn:asciiname":"L'Anglais",
    "gn:country_code":"GP",
    "gn:dem":33,
    "gn:feature_class":"P",
    "gn:feature_code":"PPL",
    "gn:name":"L\u2019Anglais",
    "gn:population":0,
    "gn:timezone":"America/Guadeloupe",
    "iso:country":"GP",
    "name:fra_x_preferred":[
        "L\u2019Anglais"
    ],
    "wof:name":"L'Anglais",
    "wof:placetype":"locality"
},
  "geometry": {"coordinates":[-61.30467,16.32328],"type":"Point"}
}