{
  "type": "Feature",
  "properties": {
    "gn:admin1_code":"00",
    "gn:asciiname":"Convenance",
    "gn:country_code":"GP",
    "gn:dem":41,
    "gn:feature_class":"P",
    "gn:feature_code":"PPL",
    "gn:name":"Convenance",
    "gn:population":0,
    "gn:timezone":"America/Guadeloupe",
    "iso:country":"GP",
    "name:fra_x_preferred":[
        "Convenance"
    ],
    "wof:name":"Convenance",
    "wof:placetype":"locality"
},
  "geometry": {"coordinates":[-61.59865,16.23871],"type":"Point"}
}