{
  "type": "Feature",
  "properties": {
    "gn:admin1_code":"00",
    "gn:asciiname":"Morne a Jules",
    "gn:country_code":"GP",
    "gn:dem":52,
    "gn:feature_class":"P",
    "gn:feature_code":"PPL",
    "gn:name":"Morne \u00e0 Jules",
    "gn:population":0,
    "gn:timezone":"America/Guadeloupe",
    "iso:country":"GP",
    "name:fra_x_preferred":[
        "Morne \u00e0 Jules"
    ],
    "wof:name":"Morne a Jules",
    "wof:placetype":"locality"
},
  "geometry": {"coordinates":[-61.76358000000001,16.07317],"type":"Point"}
}