{
  "type": "Feature",
  "properties": {
    "gn:admin1_code":"00",
    "gn:asciiname":"L'Heurissy",
    "gn:country_code":"GP",
    "gn:dem":97,
    "gn:feature_class":"P",
    "gn:feature_code":"PPLL",
    "gn:name":"L\u2019Heurissy",
    "gn:population":0,
    "gn:timezone":"America/Guadeloupe",
    "iso:country":"GP",
    "name:fra_x_preferred":[
        "L\u2019Heurissy"
    ],
    "wof:name":"L'Heurissy",
    "wof:placetype":"locality"
},
  "geometry": {"coordinates":[-61.41825,16.2394],"type":"Point"}
}