{
  "type": "Feature",
  "properties": {
    "gn:admin1_code":"00",
    "gn:asciiname":"Bas Village",
    "gn:country_code":"GP",
    "gn:dem":134,
    "gn:feature_class":"P",
    "gn:feature_code":"PPL",
    "gn:name":"Bas Village",
    "gn:population":0,
    "gn:timezone":"America/Guadeloupe",
    "iso:country":"GP",
    "name:fra_x_preferred":[
        "Bas Village"
    ],
    "wof:name":"Bas Village",
    "wof:placetype":"locality"
},
  "geometry": {"coordinates":[-61.76693,16.10004],"type":"Point"}
}