{
  "type": "Feature",
  "properties": {
    "gn:admin1_code":"00",
    "gn:asciiname":"Trianon",
    "gn:country_code":"GP",
    "gn:dem":112,
    "gn:feature_class":"P",
    "gn:feature_code":"PPLL",
    "gn:name":"Trianon",
    "gn:population":0,
    "gn:timezone":"America/Guadeloupe",
    "iso:country":"GP",
    "name:cat_x_preferred":[
        "Trianon"
    ],
    "name:deu_x_preferred":[
        "Trianon"
    ],
    "name:epo_x_preferred":[
        "Trianon"
    ],
    "name:fin_x_preferred":[
        "Trianon"
    ],
    "name:fra_x_preferred":[
        "Trianon"
    ],
    "name:hun_x_preferred":[
        "Trianon"
    ],
    "name:ita_x_preferred":[
        "Trianon"
    ],
    "name:jpn_x_preferred":[
        "\u30c8\u30ea\u30a2\u30ce\u30f3"
    ],
    "name:kor_x_preferred":[
        "\ud2b8\ub9ac\uc544\ub18d"
    ],
    "name:nld_x_preferred":[
        "Trianon"
    ],
    "name:pol_x_preferred":[
        "Trianon"
    ],
    "name:por_x_preferred":[
        "Trianon"
    ],
    "name:rus_x_preferred":[
        "\u0422\u0440\u0438\u0430\u043d\u043e\u043d"
    ],
    "name:slk_x_preferred":[
        "Trianon"
    ],
    "name:spa_x_preferred":[
        "Trianon"
    ],
    "name:srp_x_preferred":[
        "\u0422\u0440\u0438\u0458\u0430\u043d\u043e\u043d"
    ],
    "name:swe_x_preferred":[
        "Trianon"
    ],
    "wof:name":"Trianon",
    "wof:placetype":"locality"
},
  "geometry": {"coordinates":[-61.62311,16.16289],"type":"Point"}
}