{
  "type": "Feature",
  "properties": {
    "gn:admin1_code":"00",
    "gn:asciiname":"Marecage",
    "gn:country_code":"GP",
    "gn:dem":101,
    "gn:feature_class":"P",
    "gn:feature_code":"PPL",
    "gn:name":"Mar\u00e9cage",
    "gn:population":0,
    "gn:timezone":"America/Guadeloupe",
    "iso:country":"GP",
    "name:fra_x_preferred":[
        "Mar\u00e9cage"
    ],
    "wof:name":"Marecage",
    "wof:placetype":"locality"
},
  "geometry": {"coordinates":[-61.27946,15.88523],"type":"Point"}
}