{
  "type": "Feature",
  "properties": {
    "gn:admin1_code":"00",
    "gn:asciiname":"Bois Joli",
    "gn:country_code":"GP",
    "gn:dem":36,
    "gn:feature_class":"P",
    "gn:feature_code":"PPL",
    "gn:name":"Bois Joli",
    "gn:population":0,
    "gn:timezone":"America/Guadeloupe",
    "iso:country":"GP",
    "name:fra_x_preferred":[
        "Bois Joli"
    ],
    "wof:name":"Bois Joli",
    "wof:placetype":"locality"
},
  "geometry": {"coordinates":[-61.49887,16.27418],"type":"Point"}
}