{
  "type": "Feature",
  "properties": {
    "gn:admin1_code":"00",
    "gn:asciiname":"Dugay",
    "gn:country_code":"GP",
    "gn:dem":156,
    "gn:feature_class":"P",
    "gn:feature_code":"PPL",
    "gn:name":"Dugay",
    "gn:population":0,
    "gn:timezone":"America/Guadeloupe",
    "iso:country":"GP",
    "name:fra_x_preferred":[
        "Dugay"
    ],
    "wof:name":"Dugay",
    "wof:placetype":"locality"
},
  "geometry": {"coordinates":[-61.24658,15.89152],"type":"Point"}
}