{
  "type": "Feature",
  "properties": {
    "gn:admin1_code":"00",
    "gn:asciiname":"Lambert",
    "gn:country_code":"GP",
    "gn:dem":116,
    "gn:feature_class":"P",
    "gn:feature_code":"PPL",
    "gn:name":"Lambert",
    "gn:population":0,
    "gn:timezone":"America/Guadeloupe",
    "iso:country":"GP",
    "name:cat_x_preferred":[
        "Lambert"
    ],
    "name:ceb_x_preferred":[
        "Lambert"
    ],
    "name:ces_x_preferred":[
        "Lambert"
    ],
    "name:deu_x_preferred":[
        "Lambert"
    ],
    "name:epo_x_preferred":[
        "Lambert"
    ],
    "name:est_x_preferred":[
        "Lambert"
    ],
    "name:fas_x_preferred":[
        "\u0644\u0645\u0628\u0631\u062a"
    ],
    "name:fin_x_preferred":[
        "Lambert"
    ],
    "name:fra_x_preferred":[
        "Lambert"
    ],
    "name:heb_x_preferred":[
        "\u05dc\u05de\u05d1\u05e8\u05d8"
    ],
    "name:ita_x_preferred":[
        "Lambert"
    ],
    "name:jpn_x_preferred":[
        "\u30e9\u30f3\u30d0\u30fc\u30c8"
    ],
    "name:kor_x_preferred":[
        "\ub7a8\ubc84\ud2b8"
    ],
    "name:lav_x_preferred":[
        "Lambert"
    ],
    "name:nld_x_preferred":[
        "Lambert"
    ],
    "name:pol_x_preferred":[
        "Lambert"
    ],
    "name:por_x_preferred":[
        "Lambert"
    ],
    "name:rus_x_preferred":[
        "\u041b\u0430\u043c\u0431\u0435\u0440\u0442"
    ],
    "name:slv_x_preferred":[
        "Lambert"
    ],
    "name:spa_x_preferred":[
        "Lambert"
    ],
    "name:srp_x_preferred":[
        "\u041b\u0430\u043c\u0431\u0435\u0440\u0442"
    ],
    "name:swe_x_preferred":[
        "Lambert"
    ],
    "name:ukr_x_preferred":[
        "\u041b\u0430\u043c\u0431\u0435\u0440\u0442"
    ],
    "name:vol_x_preferred":[
        "Lambert"
    ],
    "wof:name":"Lambert",
    "wof:placetype":"locality"
},
  "geometry": {"coordinates":[-61.43592,16.25134],"type":"Point"}
}