{
  "type": "Feature",
  "properties": {
    "gn:admin1_code":"00",
    "gn:asciiname":"Lambert",
    "gn:country_code":"GP",
    "gn:dem":116,
    "gn:feature_class":"P",
    "gn:feature_code":"PPL",
    "gn:name":"Lambert",
    "gn:population":0,
    "gn:timezone":"America/Guadeloupe",
    "iso:country":"GP",
    "name:fra_x_preferred":[
        "Lambert"
    ],
    "wof:name":"Lambert",
    "wof:placetype":"locality"
},
  "geometry": {"coordinates":[-61.43592,16.25134],"type":"Point"}
}