{
  "type": "Feature",
  "properties": {
    "gn:admin1_code":"00",
    "gn:asciiname":"Bois de Rose",
    "gn:country_code":"GP",
    "gn:dem":61,
    "gn:feature_class":"P",
    "gn:feature_code":"PPL",
    "gn:name":"Bois de Rose",
    "gn:population":0,
    "gn:timezone":"America/Guadeloupe",
    "iso:country":"GP",
    "name:fra_x_preferred":[
        "Bois de Rose"
    ],
    "wof:name":"Bois de Rose",
    "wof:placetype":"locality"
},
  "geometry": {"coordinates":[-61.627,16.20651],"type":"Point"}
}