{
  "type": "Feature",
  "properties": {
    "gn:admin1_code":"GP",
    "gn:admin2_code":"971",
    "gn:admin3_code":"9711.0",
    "gn:admin4_code":"97109.0",
    "gn:asciiname":"Champfleury",
    "gn:country_code":"GP",
    "gn:dem":258,
    "gn:feature_class":"P",
    "gn:feature_code":"PPL",
    "gn:name":"Champfleury",
    "gn:population":0,
    "gn:timezone":"America/Guadeloupe",
    "iso:country":"GP",
    "name:fra_x_preferred":[
        "Champfleury"
    ],
    "wof:name":"Champfleury",
    "wof:placetype":"locality"
},
  "geometry": {"coordinates":[-61.68035,15.98358],"type":"Point"}
}