{
  "type": "Feature",
  "properties": {
    "gn:admin1_code":"GP",
    "gn:admin2_code":"971",
    "gn:admin3_code":"9711.0",
    "gn:admin4_code":"97109.0",
    "gn:asciiname":"Champfleury",
    "gn:country_code":"GP",
    "gn:dem":258,
    "gn:feature_class":"P",
    "gn:feature_code":"PPL",
    "gn:name":"Champfleury",
    "gn:population":0,
    "gn:timezone":"America/Guadeloupe",
    "iso:country":"GP",
    "name:ces_x_preferred":[
        "Champfleury"
    ],
    "name:dan_x_preferred":[
        "Jules Champfleury"
    ],
    "name:deu_x_preferred":[
        "Jules Champfleury"
    ],
    "name:fas_x_preferred":[
        "\u0698\u0648\u0644 \u0634\u0627\u0645\u0641\u0644\u0648\u0631\u06cc"
    ],
    "name:fra_x_preferred":[
        "Champfleury"
    ],
    "name:ita_x_preferred":[
        "Jules Champfleury"
    ],
    "name:mkd_x_preferred":[
        "\u0428\u0430\u043d\u0444\u043b\u0435\u0440\u0438"
    ],
    "name:nld_x_preferred":[
        "Jules Champfleury"
    ],
    "name:pcd_x_preferred":[
        "Jules Champfleury"
    ],
    "name:pol_x_preferred":[
        "Jules Champfleury"
    ],
    "name:ron_x_preferred":[
        "Jules Champfleury"
    ],
    "name:rus_x_preferred":[
        "\u0428\u0430\u043d\u0444\u043b\u0451\u0440\u0438"
    ],
    "name:spa_x_preferred":[
        "Jules Champfleury"
    ],
    "name:swe_x_preferred":[
        "Jules Champfleury"
    ],
    "name:ukr_x_preferred":[
        "\u0428\u0430\u043d\u0444\u043b\u0435\u0440\u0456"
    ],
    "wof:name":"Champfleury",
    "wof:placetype":"locality"
},
  "geometry": {"coordinates":[-61.68035,15.98358],"type":"Point"}
}