{
  "type": "Feature",
  "properties": {
    "gn:admin1_code":"00",
    "gn:asciiname":"Belle Mare",
    "gn:country_code":"GP",
    "gn:dem":34,
    "gn:feature_class":"P",
    "gn:feature_code":"PPL",
    "gn:name":"Belle Mare",
    "gn:population":0,
    "gn:timezone":"America/Guadeloupe",
    "iso:country":"GP",
    "name:fra_x_preferred":[
        "Belle Mare"
    ],
    "wof:name":"Belle Mare",
    "wof:placetype":"locality"
},
  "geometry": {"coordinates":[-61.3076,16.31232],"type":"Point"}
}