{
  "type": "Feature",
  "properties": {
    "gn:admin1_code":"00",
    "gn:asciiname":"Beautiran",
    "gn:country_code":"GP",
    "gn:dem":5,
    "gn:feature_class":"P",
    "gn:feature_code":"PPL",
    "gn:name":"Beautiran",
    "gn:population":0,
    "gn:timezone":"America/Guadeloupe",
    "iso:country":"GP",
    "name:fra_x_preferred":[
        "Beautiran"
    ],
    "wof:name":"Beautiran",
    "wof:placetype":"locality"
},
  "geometry": {"coordinates":[-61.50337,16.38658],"type":"Point"}
}