{
  "type": "Feature",
  "properties": {
    "gn:admin1_code":"00",
    "gn:asciiname":"Beautiran",
    "gn:country_code":"GP",
    "gn:dem":5,
    "gn:feature_class":"P",
    "gn:feature_code":"PPL",
    "gn:name":"Beautiran",
    "gn:population":0,
    "gn:timezone":"America/Guadeloupe",
    "iso:country":"GP",
    "name:bug_x_preferred":[
        "Beautiran"
    ],
    "name:cat_x_preferred":[
        "Bautiran"
    ],
    "name:ceb_x_preferred":[
        "Beautiran"
    ],
    "name:deu_x_preferred":[
        "Beautiran"
    ],
    "name:eus_x_preferred":[
        "Bautiran"
    ],
    "name:fra_x_preferred":[
        "Beautiran"
    ],
    "name:hun_x_preferred":[
        "Beautiran"
    ],
    "name:ind_x_preferred":[
        "Beautiran"
    ],
    "name:ita_x_preferred":[
        "Beautiran"
    ],
    "name:kaz_x_preferred":[
        "\u0411\u043e\u0442\u0438\u0440\u0430\u043d"
    ],
    "name:lat_x_preferred":[
        "Beautiran"
    ],
    "name:mlg_x_preferred":[
        "Beautiran"
    ],
    "name:msa_x_preferred":[
        "Beautiran"
    ],
    "name:nld_x_preferred":[
        "Beautiran"
    ],
    "name:nor_x_preferred":[
        "Beautiran"
    ],
    "name:oci_x_preferred":[
        "Bautiran"
    ],
    "name:pms_x_preferred":[
        "Beautiran"
    ],
    "name:pol_x_preferred":[
        "Beautiran"
    ],
    "name:por_x_preferred":[
        "Beautiran"
    ],
    "name:ron_x_preferred":[
        "Beautiran"
    ],
    "name:rus_x_preferred":[
        "\u0411\u043e\u0442\u0438\u0440\u0430\u043d"
    ],
    "name:slk_x_preferred":[
        "Beautiran"
    ],
    "name:spa_x_preferred":[
        "Beautiran"
    ],
    "name:sqi_x_preferred":[
        "Beautiran"
    ],
    "name:srp_x_preferred":[
        "\u0411\u043e\u0442\u0438\u0440\u0430\u043d"
    ],
    "name:swe_x_preferred":[
        "Beautiran"
    ],
    "name:ukr_x_preferred":[
        "\u0411\u043e\u0442\u0456\u0440\u0430\u043d"
    ],
    "name:uzb_x_preferred":[
        "Beautiran"
    ],
    "name:vie_x_preferred":[
        "Beautiran"
    ],
    "name:vol_x_preferred":[
        "Beautiran"
    ],
    "name:war_x_preferred":[
        "Beautiran"
    ],
    "name:zho_x_preferred":[
        "\u535a\u8482\u6717"
    ],
    "wof:name":"Beautiran",
    "wof:placetype":"locality"
},
  "geometry": {"coordinates":[-61.50337,16.38658],"type":"Point"}
}