{
  "type": "Feature",
  "properties": {
    "gn:admin1_code":"00",
    "gn:asciiname":"Les Galbas",
    "gn:country_code":"GP",
    "gn:dem":5,
    "gn:feature_class":"P",
    "gn:feature_code":"PPL",
    "gn:name":"Les Galbas",
    "gn:population":0,
    "gn:timezone":"America/Guadeloupe",
    "iso:country":"GP",
    "name:fra_x_preferred":[
        "Les Galbas"
    ],
    "wof:name":"Les Galbas",
    "wof:placetype":"locality"
},
  "geometry": {"coordinates":[-61.39366,16.22358],"type":"Point"}
}