{
  "type": "Feature",
  "properties": {
    "gn:admin1_code":"00",
    "gn:asciiname":"Desbonnes",
    "gn:country_code":"GP",
    "gn:dem":70,
    "gn:feature_class":"P",
    "gn:feature_code":"PPL",
    "gn:name":"Desbonnes",
    "gn:population":0,
    "gn:timezone":"America/Guadeloupe",
    "iso:country":"GP",
    "name:fra_x_preferred":[
        "Desbonnes"
    ],
    "wof:name":"Desbonnes",
    "wof:placetype":"locality"
},
  "geometry": {"coordinates":[-61.65812,16.23427],"type":"Point"}
}