{
  "type": "Feature",
  "properties": {
    "gn:admin1_code":"00",
    "gn:asciiname":"Taillefer",
    "gn:country_code":"GP",
    "gn:dem":148,
    "gn:feature_class":"P",
    "gn:feature_code":"PPL",
    "gn:name":"Taillefer",
    "gn:population":0,
    "gn:timezone":"America/Guadeloupe",
    "iso:country":"GP",
    "name:fra_x_preferred":[
        "Taillefer"
    ],
    "wof:name":"Taillefer",
    "wof:placetype":"locality"
},
  "geometry": {"coordinates":[-61.29265,15.96261],"type":"Point"}
}