{
  "type": "Feature",
  "properties": {
    "gn:admin1_code":"00",
    "gn:asciiname":"Dunoyer",
    "gn:country_code":"GP",
    "gn:dem":20,
    "gn:feature_class":"P",
    "gn:feature_code":"PPL",
    "gn:name":"Dunoyer",
    "gn:population":0,
    "gn:timezone":"America/Guadeloupe",
    "iso:country":"GP",
    "name:fra_x_preferred":[
        "Dunoyer"
    ],
    "wof:name":"Dunoyer",
    "wof:placetype":"locality"
},
  "geometry": {"coordinates":[-61.46532,16.208],"type":"Point"}
}