{
  "type": "Feature",
  "properties": {
    "gn:admin1_code":"00",
    "gn:asciiname":"Vauchelet",
    "gn:country_code":"GP",
    "gn:dem":332,
    "gn:feature_class":"P",
    "gn:feature_code":"PPL",
    "gn:name":"Vauchelet",
    "gn:population":0,
    "gn:timezone":"America/Guadeloupe",
    "iso:country":"GP",
    "name:fra_x_preferred":[
        "Vauchelet"
    ],
    "wof:name":"Vauchelet",
    "wof:placetype":"locality"
},
  "geometry": {"coordinates":[-61.61818,16.02633],"type":"Point"}
}