{
  "type": "Feature",
  "properties": {
    "gn:admin1_code":"00",
    "gn:asciiname":"Camp Dugommier",
    "gn:country_code":"GP",
    "gn:dem":16,
    "gn:feature_class":"P",
    "gn:feature_code":"PPL",
    "gn:name":"Camp Dugommier",
    "gn:population":0,
    "gn:timezone":"America/Guadeloupe",
    "iso:country":"GP",
    "name:fra_x_preferred":[
        "Camp Dugommier"
    ],
    "wof:name":"Camp Dugommier",
    "wof:placetype":"locality"
},
  "geometry": {"coordinates":[-61.56262,16.25677],"type":"Point"}
}