{
  "type": "Feature",
  "properties": {
    "gn:admin1_code":"00",
    "gn:asciiname":"Le Bois d'Inde",
    "gn:country_code":"GP",
    "gn:dem":33,
    "gn:feature_class":"P",
    "gn:feature_code":"PPLL",
    "gn:name":"Le Bois d\u2019Inde",
    "gn:population":0,
    "gn:timezone":"America/Guadeloupe",
    "iso:country":"GP",
    "name:fra_x_preferred":[
        "Le Bois d\u2019Inde"
    ],
    "wof:name":"Le Bois d'Inde",
    "wof:placetype":"locality"
},
  "geometry": {"coordinates":[-61.68742,16.27155],"type":"Point"}
}