{
  "type": "Feature",
  "properties": {
    "gn:admin1_code":"00",
    "gn:asciiname":"Blondiniere",
    "gn:country_code":"GP",
    "gn:dem":109,
    "gn:feature_class":"P",
    "gn:feature_code":"PPLL",
    "gn:name":"Blondini\u00e8re",
    "gn:population":0,
    "gn:timezone":"America/Guadeloupe",
    "iso:country":"GP",
    "name:fra_x_preferred":[
        "Blondini\u00e8re"
    ],
    "wof:name":"Blondiniere",
    "wof:placetype":"locality"
},
  "geometry": {"coordinates":[-61.58734000000001,16.04044],"type":"Point"}
}