{
  "type": "Feature",
  "properties": {
    "gn:admin1_code":"GP",
    "gn:admin2_code":"971",
    "gn:admin3_code":"9712.0",
    "gn:admin4_code":"97128.0",
    "gn:asciiname":"Surgy",
    "gn:country_code":"GP",
    "gn:dem":37,
    "gn:feature_class":"P",
    "gn:feature_code":"PPL",
    "gn:name":"Surgy",
    "gn:population":0,
    "gn:timezone":"America/Guadeloupe",
    "iso:country":"GP",
    "name:und_x_variant":[
        "De Surgy",
        "Surgy"
    ],
    "wof:name":"Surgy",
    "wof:placetype":"locality"
},
  "geometry": {"coordinates":[-61.34041,16.26278],"type":"Point"}
}