{
  "type": "Feature",
  "properties": {
    "gn:admin1_code":"GP",
    "gn:admin2_code":"971",
    "gn:admin3_code":"9712.0",
    "gn:admin4_code":"97128.0",
    "gn:asciiname":"Surgy",
    "gn:country_code":"GP",
    "gn:dem":37,
    "gn:feature_class":"P",
    "gn:feature_code":"PPL",
    "gn:name":"Surgy",
    "gn:population":0,
    "gn:timezone":"America/Guadeloupe",
    "iso:country":"GP",
    "name:cat_x_preferred":[
        "Surgy"
    ],
    "name:ceb_x_preferred":[
        "Surgy"
    ],
    "name:deu_x_preferred":[
        "Surgy"
    ],
    "name:eus_x_preferred":[
        "Surgy"
    ],
    "name:fra_x_preferred":[
        "Surgy"
    ],
    "name:hun_x_preferred":[
        "Surgy"
    ],
    "name:ita_x_preferred":[
        "Surgy"
    ],
    "name:kaz_x_preferred":[
        "\u0421\u044e\u0440\u0436\u0438"
    ],
    "name:lat_x_preferred":[
        "Surgy"
    ],
    "name:msa_x_preferred":[
        "Surgy"
    ],
    "name:nld_x_preferred":[
        "Surgy"
    ],
    "name:oci_x_preferred":[
        "Surgy"
    ],
    "name:pms_x_preferred":[
        "Surgy"
    ],
    "name:pol_x_preferred":[
        "Surgy"
    ],
    "name:por_x_preferred":[
        "Surgy"
    ],
    "name:ron_x_preferred":[
        "Surgy"
    ],
    "name:slk_x_preferred":[
        "Surgy"
    ],
    "name:spa_x_preferred":[
        "Surgy"
    ],
    "name:swe_x_preferred":[
        "Surgy"
    ],
    "name:ukr_x_preferred":[
        "\u0421\u044e\u0440\u0436\u0456"
    ],
    "name:und_x_variant":[
        "De Surgy"
    ],
    "name:uzb_x_preferred":[
        "Surgy"
    ],
    "name:vie_x_preferred":[
        "Surgy"
    ],
    "name:vol_x_preferred":[
        "Surgy"
    ],
    "name:war_x_preferred":[
        "Surgy"
    ],
    "name:zho_x_preferred":[
        "\u53d9\u5c14\u5409"
    ],
    "wof:name":"Surgy",
    "wof:placetype":"locality"
},
  "geometry": {"coordinates":[-61.34041,16.26278],"type":"Point"}
}