{
  "type": "Feature",
  "properties": {
    "gn:admin1_code":"00",
    "gn:asciiname":"Pelletan",
    "gn:country_code":"GP",
    "gn:dem":21,
    "gn:feature_class":"P",
    "gn:feature_code":"PPL",
    "gn:name":"Pelletan",
    "gn:population":0,
    "gn:timezone":"America/Guadeloupe",
    "iso:country":"GP",
    "name:deu_x_preferred":[
        "Pelletan"
    ],
    "name:fra_x_preferred":[
        "Pelletan"
    ],
    "name:rus_x_preferred":[
        "\u041f\u0435\u043b\u044c\u0442\u0430\u043d"
    ],
    "name:swe_x_preferred":[
        "Pelletan"
    ],
    "wof:name":"Pelletan",
    "wof:placetype":"locality"
},
  "geometry": {"coordinates":[-61.47456,16.42353],"type":"Point"}
}