{
  "type": "Feature",
  "properties": {
    "gn:admin1_code":"GP",
    "gn:admin2_code":"971",
    "gn:admin3_code":"9712.0",
    "gn:admin4_code":"97101.0",
    "gn:asciiname":"L'Ilet",
    "gn:country_code":"GP",
    "gn:dem":15,
    "gn:feature_class":"P",
    "gn:feature_code":"PPL",
    "gn:name":"L\u2019\u00celet",
    "gn:population":0,
    "gn:timezone":"America/Guadeloupe",
    "iso:country":"GP",
    "wof:name":"L'Ilet",
    "wof:placetype":"locality"
},
  "geometry": {"coordinates":[-61.51667,16.28333],"type":"Point"}
}