{
  "type": "Feature",
  "properties": {
    "gn:admin1_code":"GP",
    "gn:admin2_code":"971",
    "gn:admin3_code":"9712.0",
    "gn:admin4_code":"97112.0",
    "gn:asciiname":"Moringlane",
    "gn:country_code":"GP",
    "gn:dem":72,
    "gn:feature_class":"P",
    "gn:feature_code":"PPL",
    "gn:name":"Moringlane",
    "gn:population":0,
    "gn:timezone":"America/Guadeloupe",
    "iso:country":"GP",
    "name:fra_x_preferred":[
        "Moringlane"
    ],
    "wof:name":"Moringlane",
    "wof:placetype":"locality"
},
  "geometry": {"coordinates":[-61.30363000000001,15.92499],"type":"Point"}
}