{
  "type": "Feature",
  "properties": {
    "gn:admin1_code":"00",
    "gn:asciiname":"Petit Perou",
    "gn:country_code":"GP",
    "gn:dem":12,
    "gn:feature_class":"P",
    "gn:feature_code":"PPL",
    "gn:name":"Petit P\u00e9rou",
    "gn:population":0,
    "gn:timezone":"America/Guadeloupe",
    "iso:country":"GP",
    "name:fra_x_preferred":[
        "Petit P\u00e9rou"
    ],
    "wof:name":"Petit Perou",
    "wof:placetype":"locality"
},
  "geometry": {"coordinates":[-61.56044,16.05365],"type":"Point"}
}