{
  "type": "Feature",
  "properties": {
    "gn:admin1_code":"00",
    "gn:asciiname":"Faugas",
    "gn:country_code":"GP",
    "gn:dem":45,
    "gn:feature_class":"P",
    "gn:feature_code":"PPL",
    "gn:name":"Faugas",
    "gn:population":0,
    "gn:timezone":"America/Guadeloupe",
    "iso:country":"GP",
    "name:fra_x_preferred":[
        "Faugas"
    ],
    "wof:name":"Faugas",
    "wof:placetype":"locality"
},
  "geometry": {"coordinates":[-61.67059,16.25864],"type":"Point"}
}