{
  "type": "Feature",
  "properties": {
    "gn:admin1_code":"GP",
    "gn:admin2_code":"971",
    "gn:admin3_code":"9711.0",
    "gn:admin4_code":"97111.0",
    "gn:asciiname":"Bas-Vent",
    "gn:country_code":"GP",
    "gn:dem":28,
    "gn:feature_class":"P",
    "gn:feature_code":"PPL",
    "gn:name":"Bas-Vent",
    "gn:population":0,
    "gn:timezone":"America/Guadeloupe",
    "iso:country":"GP",
    "name:fra_x_preferred":[
        "Bas-Vent"
    ],
    "name:und_x_variant":[
        "Bas Vent"
    ],
    "wof:name":"Bas-Vent",
    "wof:placetype":"locality"
},
  "geometry": {"coordinates":[-61.77072,16.3423],"type":"Point"}
}