{
  "type": "Feature",
  "properties": {
    "gn:admin1_code":"00",
    "gn:asciiname":"La Frechou",
    "gn:country_code":"GP",
    "gn:dem":39,
    "gn:feature_class":"P",
    "gn:feature_code":"PPLL",
    "gn:name":"La Fr\u00e9chou",
    "gn:population":0,
    "gn:timezone":"America/Guadeloupe",
    "iso:country":"GP",
    "name:fra_x_preferred":[
        "La Fr\u00e9chou"
    ],
    "wof:name":"La Frechou",
    "wof:placetype":"locality"
},
  "geometry": {"coordinates":[-61.4744,16.21857],"type":"Point"}
}