{
  "type": "Feature",
  "properties": {
    "gn:admin1_code":"GP",
    "gn:admin2_code":"971",
    "gn:admin3_code":"9711.0",
    "gn:admin4_code":"97121.0",
    "gn:asciiname":"Grande Plaine",
    "gn:country_code":"GP",
    "gn:dem":13,
    "gn:feature_class":"P",
    "gn:feature_code":"PPL",
    "gn:name":"Grande Plaine",
    "gn:population":0,
    "gn:timezone":"America/Guadeloupe",
    "iso:country":"GP",
    "name:und_x_variant":[
        "La Grande Plaine",
        "Grande Plaine"
    ],
    "wof:name":"Grande Plaine",
    "wof:placetype":"locality"
},
  "geometry": {"coordinates":[-61.77633,16.20725],"type":"Point"}
}