{
  "type": "Feature",
  "properties": {
    "gn:admin1_code":"00",
    "gn:asciiname":"Absalon",
    "gn:country_code":"GP",
    "gn:dem":456,
    "gn:feature_class":"P",
    "gn:feature_code":"PPL",
    "gn:name":"Absalon",
    "gn:population":0,
    "gn:timezone":"America/Guadeloupe",
    "iso:country":"GP",
    "name:bel_x_preferred":[
        "\u0410\u0431\u0441\u0430\u043b\u043e\u043d"
    ],
    "name:cat_x_preferred":[
        "Absalon"
    ],
    "name:ces_x_preferred":[
        "Absalon"
    ],
    "name:dan_x_preferred":[
        "Absalon"
    ],
    "name:est_x_preferred":[
        "Absalon"
    ],
    "name:eus_x_preferred":[
        "Absalon"
    ],
    "name:fin_x_preferred":[
        "Absalon"
    ],
    "name:fra_x_preferred":[
        "Absalon"
    ],
    "name:isl_x_preferred":[
        "Absalon erkibiskup"
    ],
    "name:ita_x_preferred":[
        "Absalon"
    ],
    "name:jpn_x_preferred":[
        "\u30a2\u30d6\u30b5\u30ed\u30f3"
    ],
    "name:nds_x_preferred":[
        "Absalon"
    ],
    "name:nld_x_preferred":[
        "Absalon"
    ],
    "name:nor_x_preferred":[
        "Absalon"
    ],
    "name:pol_x_preferred":[
        "Absalon"
    ],
    "name:ron_x_preferred":[
        "Absalon"
    ],
    "name:rus_x_preferred":[
        "\u0410\u0431\u0441\u0430\u043b\u043e\u043d"
    ],
    "name:slk_x_preferred":[
        "Absalon"
    ],
    "name:swe_x_preferred":[
        "Absalon Hvide"
    ],
    "name:ukr_x_preferred":[
        "\u0410\u0431\u0441\u0430\u043b\u043e\u043d"
    ],
    "name:vie_x_preferred":[
        "Absalon"
    ],
    "wof:name":"Absalon",
    "wof:placetype":"locality"
},
  "geometry": {"coordinates":[-61.73579,16.11717],"type":"Point"}
}