{
  "type": "Feature",
  "properties": {
    "gn:admin1_code":"00",
    "gn:asciiname":"Absalon",
    "gn:country_code":"GP",
    "gn:dem":456,
    "gn:feature_class":"P",
    "gn:feature_code":"PPL",
    "gn:name":"Absalon",
    "gn:population":0,
    "gn:timezone":"America/Guadeloupe",
    "iso:country":"GP",
    "name:fra_x_preferred":[
        "Absalon"
    ],
    "wof:name":"Absalon",
    "wof:placetype":"locality"
},
  "geometry": {"coordinates":[-61.73579,16.11717],"type":"Point"}
}