{
  "type": "Feature",
  "properties": {
    "gn:admin1_code":"00",
    "gn:asciiname":"Lolo",
    "gn:country_code":"GP",
    "gn:dem":57,
    "gn:feature_class":"P",
    "gn:feature_code":"PPL",
    "gn:name":"Lolo",
    "gn:population":0,
    "gn:timezone":"America/Guadeloupe",
    "iso:country":"GP",
    "name:fra_x_preferred":[
        "Lolo"
    ],
    "wof:name":"Lolo",
    "wof:placetype":"locality"
},
  "geometry": {"coordinates":[-61.43275,16.31258],"type":"Point"}
}