{
  "type": "Feature",
  "properties": {
    "gn:admin1_code":"00",
    "gn:asciiname":"Tacy",
    "gn:country_code":"GP",
    "gn:dem":143,
    "gn:feature_class":"P",
    "gn:feature_code":"PPL",
    "gn:name":"Tacy",
    "gn:population":0,
    "gn:timezone":"America/Guadeloupe",
    "iso:country":"GP",
    "name:fra_x_preferred":[
        "Tacy"
    ],
    "wof:name":"Tacy",
    "wof:placetype":"locality"
},
  "geometry": {"coordinates":[-61.21601999999999,15.92983],"type":"Point"}
}