{
  "type": "Feature",
  "properties": {
    "gn:admin1_code":"00",
    "gn:asciiname":"Ruillier",
    "gn:country_code":"GP",
    "gn:dem":25,
    "gn:feature_class":"P",
    "gn:feature_code":"PPLL",
    "gn:name":"Ruillier",
    "gn:population":0,
    "gn:timezone":"America/Guadeloupe",
    "iso:country":"GP",
    "name:fra_x_preferred":[
        "Ruillier"
    ],
    "wof:name":"Ruillier",
    "wof:placetype":"locality"
},
  "geometry": {"coordinates":[-61.4436,16.43839],"type":"Point"}
}