{
  "type": "Feature",
  "properties": {
    "gn:admin1_code":"00",
    "gn:asciiname":"Pavillot",
    "gn:country_code":"GP",
    "gn:dem":16,
    "gn:feature_class":"P",
    "gn:feature_code":"PPL",
    "gn:name":"Pavillot",
    "gn:population":0,
    "gn:timezone":"America/Guadeloupe",
    "iso:country":"GP",
    "name:fra_x_preferred":[
        "Pavillot"
    ],
    "wof:name":"Pavillot",
    "wof:placetype":"locality"
},
  "geometry": {"coordinates":[-61.49735,16.45715],"type":"Point"}
}