{
  "type": "Feature",
  "properties": {
    "gn:admin1_code":"GP",
    "gn:admin2_code":"971",
    "gn:admin3_code":"9712.0",
    "gn:admin4_code":"97113.0",
    "gn:asciiname":"Mare Gaillard",
    "gn:country_code":"GP",
    "gn:dem":69,
    "gn:feature_class":"P",
    "gn:feature_code":"PPL",
    "gn:name":"Mare Gaillard",
    "gn:population":0,
    "gn:timezone":"America/Guadeloupe",
    "iso:country":"GP",
    "name:und_x_variant":[
        "Marc Gaillard",
        "Mare Gaillard"
    ],
    "wof:name":"Mare Gaillard",
    "wof:placetype":"locality"
},
  "geometry": {"coordinates":[-61.4393,16.2153],"type":"Point"}
}