{
  "type": "Feature",
  "properties": {
    "gn:admin1_code":"00",
    "gn:asciiname":"Gaigneron",
    "gn:country_code":"GP",
    "gn:dem":126,
    "gn:feature_class":"P",
    "gn:feature_code":"PPL",
    "gn:name":"Gaigneron",
    "gn:population":0,
    "gn:timezone":"America/Guadeloupe",
    "iso:country":"GP",
    "name:fra_x_preferred":[
        "Gaigneron"
    ],
    "wof:name":"Gaigneron",
    "wof:placetype":"locality"
},
  "geometry": {"coordinates":[-61.63825,15.97398],"type":"Point"}
}