{
  "type": "Feature",
  "properties": {
    "gn:admin1_code":"00",
    "gn:asciiname":"Bonne Terre",
    "gn:country_code":"GP",
    "gn:dem":21,
    "gn:feature_class":"P",
    "gn:feature_code":"PPL",
    "gn:name":"Bonne Terre",
    "gn:population":0,
    "gn:timezone":"America/Guadeloupe",
    "iso:country":"GP",
    "name:fra_x_preferred":[
        "Bonne Terre"
    ],
    "wof:name":"Bonne Terre",
    "wof:placetype":"locality"
},
  "geometry": {"coordinates":[-61.45022,16.35459],"type":"Point"}
}