{
  "type": "Feature",
  "properties": {
    "gn:admin1_code":"00",
    "gn:asciiname":"Saint-Paul",
    "gn:country_code":"GP",
    "gn:dem":112,
    "gn:feature_class":"P",
    "gn:feature_code":"PPL",
    "gn:name":"Saint-Paul",
    "gn:population":0,
    "gn:timezone":"America/Guadeloupe",
    "iso:country":"GP",
    "name:fra_x_preferred":[
        "Saint-Paul"
    ],
    "wof:name":"Saint-Paul",
    "wof:placetype":"locality"
},
  "geometry": {"coordinates":[-61.40184,16.26087],"type":"Point"}
}