{
  "type": "Feature",
  "properties": {
    "gn:admin1_code":"00",
    "gn:asciiname":"Claire Fontaine",
    "gn:country_code":"GP",
    "gn:dem":330,
    "gn:feature_class":"P",
    "gn:feature_code":"PPL",
    "gn:name":"Claire Fontaine",
    "gn:population":0,
    "gn:timezone":"America/Guadeloupe",
    "iso:country":"GP",
    "name:fra_x_preferred":[
        "Claire Fontaine"
    ],
    "wof:name":"Claire Fontaine",
    "wof:placetype":"locality"
},
  "geometry": {"coordinates":[-61.72717,16.04213],"type":"Point"}
}