{
  "type": "Feature",
  "properties": {
    "gn:admin1_code":"00",
    "gn:asciiname":"Babin",
    "gn:country_code":"GP",
    "gn:dem":36,
    "gn:feature_class":"P",
    "gn:feature_code":"PPL",
    "gn:name":"Babin",
    "gn:population":0,
    "gn:timezone":"America/Guadeloupe",
    "iso:country":"GP",
    "name:ceb_x_preferred":[
        "Babin"
    ],
    "name:ces_x_preferred":[
        "Bab\u00edn"
    ],
    "name:deu_x_preferred":[
        "Babin"
    ],
    "name:fra_x_preferred":[
        "Babin"
    ],
    "name:hye_x_preferred":[
        "\u0532\u0561\u0562\u056b\u0576"
    ],
    "name:pol_x_preferred":[
        "Babin"
    ],
    "name:rus_x_preferred":[
        "\u0411\u0430\u0431\u0438\u043d"
    ],
    "name:slv_x_preferred":[
        "Babin"
    ],
    "name:srp_x_preferred":[
        "\u0411\u0430\u0431\u0438\u043d"
    ],
    "name:ukr_x_preferred":[
        "\u0411\u0430\u0431\u0456\u043d"
    ],
    "wof:name":"Babin",
    "wof:placetype":"locality"
},
  "geometry": {"coordinates":[-61.59626,16.00741],"type":"Point"}
}