{
  "type": "Feature",
  "properties": {
    "gn:admin1_code":"00",
    "gn:asciiname":"Les Abricots",
    "gn:country_code":"GP",
    "gn:dem":42,
    "gn:feature_class":"P",
    "gn:feature_code":"PPL",
    "gn:name":"Les Abricots",
    "gn:population":0,
    "gn:timezone":"America/Guadeloupe",
    "iso:country":"GP",
    "name:fra_x_preferred":[
        "Les Abricots"
    ],
    "wof:name":"Les Abricots",
    "wof:placetype":"locality"
},
  "geometry": {"coordinates":[-61.62763,16.25013],"type":"Point"}
}