{
  "type": "Feature",
  "properties": {
    "gn:admin1_code":"00",
    "gn:asciiname":"Massy",
    "gn:country_code":"GP",
    "gn:dem":84,
    "gn:feature_class":"P",
    "gn:feature_code":"PPLL",
    "gn:name":"Massy",
    "gn:population":0,
    "gn:timezone":"America/Guadeloupe",
    "iso:country":"GP",
    "name:fra_x_preferred":[
        "Massy"
    ],
    "wof:name":"Massy",
    "wof:placetype":"locality"
},
  "geometry": {"coordinates":[-61.70685,16.31687],"type":"Point"}
}