{
  "type": "Feature",
  "properties": {
    "gn:admin1_code":"00",
    "gn:asciiname":"Massy",
    "gn:country_code":"GP",
    "gn:dem":84,
    "gn:feature_class":"P",
    "gn:feature_code":"PPLL",
    "gn:name":"Massy",
    "gn:population":0,
    "gn:timezone":"America/Guadeloupe",
    "iso:country":"GP",
    "name:cat_x_preferred":[
        "Massy"
    ],
    "name:ceb_x_preferred":[
        "Massy"
    ],
    "name:ces_x_preferred":[
        "Massy"
    ],
    "name:deu_x_preferred":[
        "Massy"
    ],
    "name:epo_x_preferred":[
        "Massy"
    ],
    "name:fra_x_preferred":[
        "Massy"
    ],
    "name:hun_x_preferred":[
        "Massy"
    ],
    "name:ind_x_preferred":[
        "Massy"
    ],
    "name:ita_x_preferred":[
        "Massy"
    ],
    "name:nds_x_preferred":[
        "Massy"
    ],
    "name:nld_x_preferred":[
        "Massy"
    ],
    "name:oci_x_preferred":[
        "Massy"
    ],
    "name:pms_x_preferred":[
        "Massy"
    ],
    "name:pol_x_preferred":[
        "Massy"
    ],
    "name:por_x_preferred":[
        "Massy"
    ],
    "name:ron_x_preferred":[
        "Massy"
    ],
    "name:slk_x_preferred":[
        "Massy"
    ],
    "name:spa_x_preferred":[
        "Massy"
    ],
    "name:swe_x_preferred":[
        "Massy"
    ],
    "name:ukr_x_preferred":[
        "\u041c\u0430\u0441\u0441\u0456"
    ],
    "wof:name":"Massy",
    "wof:placetype":"locality"
},
  "geometry": {"coordinates":[-61.70685,16.31687],"type":"Point"}
}