{
  "type": "Feature",
  "properties": {
    "gn:admin1_code":"GP",
    "gn:admin2_code":"971",
    "gn:admin3_code":"9712.0",
    "gn:admin4_code":"97108.0",
    "gn:asciiname":"Bezard",
    "gn:country_code":"GP",
    "gn:dem":148,
    "gn:feature_class":"P",
    "gn:feature_code":"PPL",
    "gn:name":"B\u00e9zard",
    "gn:population":0,
    "gn:timezone":"America/Guadeloupe",
    "iso:country":"GP",
    "name:fra_x_preferred":[
        "B\u00e9zard"
    ],
    "wof:name":"Bezard",
    "wof:placetype":"locality"
},
  "geometry": {"coordinates":[-61.23739000000001,15.93472],"type":"Point"}
}