{
  "type": "Feature",
  "properties": {
    "gn:admin1_code":"00",
    "gn:asciiname":"Salle d'Asile",
    "gn:country_code":"GP",
    "gn:dem":21,
    "gn:feature_class":"P",
    "gn:feature_code":"PPL",
    "gn:name":"Salle d\u2019Asile",
    "gn:population":0,
    "gn:timezone":"America/Guadeloupe",
    "iso:country":"GP",
    "name:fra_x_preferred":[
        "Salle d\u2019Asile"
    ],
    "wof:name":"Salle d'Asile",
    "wof:placetype":"locality"
},
  "geometry": {"coordinates":[-61.49916999999999,16.26166],"type":"Point"}
}