{
  "type": "Feature",
  "properties": {
    "gn:admin1_code":"00",
    "gn:asciiname":"Cinq Etangs",
    "gn:country_code":"GP",
    "gn:dem":42,
    "gn:feature_class":"P",
    "gn:feature_code":"PPL",
    "gn:name":"Cinq \u00c9tangs",
    "gn:population":0,
    "gn:timezone":"America/Guadeloupe",
    "iso:country":"GP",
    "name:fra_x_preferred":[
        "Cinq \u00c9tangs"
    ],
    "wof:name":"Cinq Etangs",
    "wof:placetype":"locality"
},
  "geometry": {"coordinates":[-61.35576999999999,16.27329],"type":"Point"}
}