{
  "type": "Feature",
  "properties": {
    "gn:admin1_code":"GP",
    "gn:admin2_code":"971",
    "gn:admin3_code":"9712.0",
    "gn:admin4_code":"97126.0",
    "gn:asciiname":"Cocotier",
    "gn:country_code":"GP",
    "gn:dem":113,
    "gn:feature_class":"P",
    "gn:feature_code":"PPLL",
    "gn:name":"Cocotier",
    "gn:population":0,
    "gn:timezone":"America/Guadeloupe",
    "iso:country":"GP",
    "wof:name":"Cocotier",
    "wof:placetype":"locality"
},
  "geometry": {"coordinates":[-61.29681,15.94861],"type":"Point"}
}