{
  "type": "Feature",
  "properties": {
    "gn:admin1_code":"GP",
    "gn:admin2_code":"971",
    "gn:admin3_code":"9711.0",
    "gn:admin4_code":"97114.0",
    "gn:asciiname":"Douville",
    "gn:country_code":"GP",
    "gn:dem":67,
    "gn:feature_class":"P",
    "gn:feature_code":"PPL",
    "gn:name":"Douville",
    "gn:population":0,
    "gn:timezone":"America/Guadeloupe",
    "iso:country":"GP",
    "name:fra_x_preferred":[
        "Douville"
    ],
    "wof:name":"Douville",
    "wof:placetype":"locality"
},
  "geometry": {"coordinates":[-61.59393000000001,16.14784],"type":"Point"}
}