{
  "type": "Feature",
  "properties": {
    "gn:admin1_code":"GP",
    "gn:admin2_code":"971",
    "gn:admin3_code":"9711.0",
    "gn:admin4_code":"97114.0",
    "gn:asciiname":"Douville",
    "gn:country_code":"GP",
    "gn:dem":67,
    "gn:feature_class":"P",
    "gn:feature_code":"PPL",
    "gn:name":"Douville",
    "gn:population":0,
    "gn:timezone":"America/Guadeloupe",
    "iso:country":"GP",
    "name:bug_x_preferred":[
        "Douville"
    ],
    "name:cat_x_preferred":[
        "Dovila"
    ],
    "name:ceb_x_preferred":[
        "Douville"
    ],
    "name:deu_x_preferred":[
        "Douville"
    ],
    "name:eus_x_preferred":[
        "Douville"
    ],
    "name:fra_x_preferred":[
        "Douville"
    ],
    "name:hun_x_preferred":[
        "Douville"
    ],
    "name:ita_x_preferred":[
        "Douville"
    ],
    "name:kaz_x_preferred":[
        "\u0414\u0443\u0432\u0438\u043b\u044c"
    ],
    "name:lat_x_preferred":[
        "Douville"
    ],
    "name:mlg_x_preferred":[
        "Douville"
    ],
    "name:msa_x_preferred":[
        "Douville"
    ],
    "name:nld_x_preferred":[
        "Douville"
    ],
    "name:oci_x_preferred":[
        "Dovila"
    ],
    "name:pms_x_preferred":[
        "Douville"
    ],
    "name:pol_x_preferred":[
        "Douville"
    ],
    "name:por_x_preferred":[
        "Douville"
    ],
    "name:ron_x_preferred":[
        "Douville"
    ],
    "name:slk_x_preferred":[
        "Douville"
    ],
    "name:spa_x_preferred":[
        "Douville"
    ],
    "name:srp_x_preferred":[
        "\u0414\u0443\u0432\u0438\u043b"
    ],
    "name:swe_x_preferred":[
        "Douville"
    ],
    "name:ukr_x_preferred":[
        "\u0414\u0443\u0432\u0456\u043b\u044c"
    ],
    "name:uzb_x_preferred":[
        "Douville"
    ],
    "name:vie_x_preferred":[
        "Douville"
    ],
    "name:vol_x_preferred":[
        "Douville"
    ],
    "name:war_x_preferred":[
        "Douville"
    ],
    "name:zho_x_preferred":[
        "\u675c\u7ef4\u5c14"
    ],
    "wof:name":"Douville",
    "wof:placetype":"locality"
},
  "geometry": {"coordinates":[-61.59393000000001,16.14784],"type":"Point"}
}