{
  "type": "Feature",
  "properties": {
    "gn:admin1_code":"GP",
    "gn:admin2_code":"971",
    "gn:admin3_code":"9712.0",
    "gn:admin4_code":"97126.0",
    "gn:asciiname":"La Rose Verger",
    "gn:country_code":"GP",
    "gn:dem":143,
    "gn:feature_class":"P",
    "gn:feature_code":"PPL",
    "gn:name":"La Rose Verger",
    "gn:population":0,
    "gn:timezone":"America/Guadeloupe",
    "iso:country":"GP",
    "name:fra_x_preferred":[
        "La Rose Verger"
    ],
    "name:und_x_variant":[
        "Verg\u00e9"
    ],
    "wof:name":"La Rose Verger",
    "wof:placetype":"locality"
},
  "geometry": {"coordinates":[-61.26185,15.94095],"type":"Point"}
}