{
  "type": "Feature",
  "properties": {
    "gn:admin1_code":"00",
    "gn:asciiname":"Pierrette",
    "gn:country_code":"GP",
    "gn:dem":76,
    "gn:feature_class":"P",
    "gn:feature_code":"PPL",
    "gn:name":"Pierrette",
    "gn:population":0,
    "gn:timezone":"America/Guadeloupe",
    "iso:country":"GP",
    "name:fra_x_preferred":[
        "Pierrette"
    ],
    "wof:name":"Pierrette",
    "wof:placetype":"locality"
},
  "geometry": {"coordinates":[-61.64588000000001,16.22285],"type":"Point"}
}