{
  "type": "Feature",
  "properties": {
    "gn:admin1_code":"00",
    "gn:asciiname":"Le Gretouf",
    "gn:country_code":"GP",
    "gn:dem":105,
    "gn:feature_class":"P",
    "gn:feature_code":"PPLL",
    "gn:name":"Le Gretouf",
    "gn:population":0,
    "gn:timezone":"America/Guadeloupe",
    "iso:country":"GP",
    "name:fra_x_preferred":[
        "Le Gretouf"
    ],
    "wof:name":"Le Gretouf",
    "wof:placetype":"locality"
},
  "geometry": {"coordinates":[-61.28604,15.89776],"type":"Point"}
}