{
  "type": "Feature",
  "properties": {
    "gn:admin1_code":"00",
    "gn:asciiname":"La Simoniere",
    "gn:country_code":"GP",
    "gn:dem":48,
    "gn:feature_class":"P",
    "gn:feature_code":"PPL",
    "gn:name":"La Simoni\u00e8re",
    "gn:population":0,
    "gn:timezone":"America/Guadeloupe",
    "iso:country":"GP",
    "name:fra_x_preferred":[
        "La Simoni\u00e8re"
    ],
    "wof:name":"La Simoniere",
    "wof:placetype":"locality"
},
  "geometry": {"coordinates":[-61.30649,16.26355],"type":"Point"}
}