{
  "type": "Feature",
  "properties": {
    "gn:admin1_code":"00",
    "gn:asciiname":"Le Petit Marigot",
    "gn:cc2":"GP",
    "gn:country_code":"GP",
    "gn:dem":13,
    "gn:feature_class":"P",
    "gn:feature_code":"PPL",
    "gn:name":"Le Petit Marigot",
    "gn:population":0,
    "gn:timezone":"America/Guadeloupe",
    "iso:country":"GP",
    "name:und_x_variant":[
        "Petit Marigot",
        "Le Petit Marigot"
    ],
    "wof:name":"Le Petit Marigot",
    "wof:placetype":"locality"
},
  "geometry": {"coordinates":[-61.56667,16.03333],"type":"Point"}
}