{
  "type": "Feature",
  "properties": {
    "gn:admin1_code":"00",
    "gn:asciiname":"La Darse",
    "gn:country_code":"GP",
    "gn:dem":3,
    "gn:feature_class":"P",
    "gn:feature_code":"PPLL",
    "gn:name":"La Darse",
    "gn:population":0,
    "gn:timezone":"America/Guadeloupe",
    "iso:country":"GP",
    "name:fra_x_preferred":[
        "La Darse"
    ],
    "wof:name":"La Darse",
    "wof:placetype":"locality"
},
  "geometry": {"coordinates":[-61.49591,16.37881],"type":"Point"}
}