{
  "type": "Feature",
  "properties": {
    "gn:admin1_code":"00",
    "gn:asciiname":"Fadat",
    "gn:country_code":"GP",
    "gn:dem":53,
    "gn:feature_class":"P",
    "gn:feature_code":"PPL",
    "gn:name":"Fadat",
    "gn:population":0,
    "gn:timezone":"America/Guadeloupe",
    "iso:country":"GP",
    "name:fra_x_preferred":[
        "Fadat"
    ],
    "wof:name":"Fadat",
    "wof:placetype":"locality"
},
  "geometry": {"coordinates":[-61.2453,15.98151],"type":"Point"}
}