{
  "type": "Feature",
  "properties": {
    "gn:admin1_code":"00",
    "gn:asciiname":"Bellevue Rouillere",
    "gn:country_code":"GP",
    "gn:dem":23,
    "gn:feature_class":"P",
    "gn:feature_code":"PPL",
    "gn:name":"Bellevue Rouill\u00e8re",
    "gn:population":0,
    "gn:timezone":"America/Guadeloupe",
    "iso:country":"GP",
    "name:fra_x_preferred":[
        "Bellevue Rouill\u00e8re"
    ],
    "wof:name":"Bellevue Rouillere",
    "wof:placetype":"locality"
},
  "geometry": {"coordinates":[-61.50161,16.47849],"type":"Point"}
}