{
  "type": "Feature",
  "properties": {
    "gn:admin1_code":"GP",
    "gn:admin2_code":"971",
    "gn:admin3_code":"9711.0",
    "gn:admin4_code":"97132.0",
    "gn:asciiname":"Boyer",
    "gn:country_code":"GP",
    "gn:dem":254,
    "gn:feature_class":"P",
    "gn:feature_code":"PPL",
    "gn:name":"Boyer",
    "gn:population":0,
    "gn:timezone":"America/Guadeloupe",
    "iso:country":"GP",
    "name:deu_x_preferred":[
        "Boyer"
    ],
    "wof:name":"Boyer",
    "wof:placetype":"locality"
},
  "geometry": {"coordinates":[-61.65,15.98333],"type":"Point"}
}