{
  "type": "Feature",
  "properties": {
    "gn:admin1_code":"GP",
    "gn:admin2_code":"971",
    "gn:admin3_code":"9712.0",
    "gn:admin4_code":"97128.0",
    "gn:asciiname":"Deshauteurs",
    "gn:country_code":"GP",
    "gn:dem":130,
    "gn:feature_class":"P",
    "gn:feature_code":"PPL",
    "gn:name":"Deshauteurs",
    "gn:population":0,
    "gn:timezone":"America/Guadeloupe",
    "iso:country":"GP",
    "name:fra_x_preferred":[
        "Deshauteurs"
    ],
    "wof:name":"Deshauteurs",
    "wof:placetype":"locality"
},
  "geometry": {"coordinates":[-61.43131999999999,16.25098],"type":"Point"}
}