{
  "type": "Feature",
  "properties": {
    "gn:admin1_code":"GP",
    "gn:admin2_code":"971",
    "gn:admin3_code":"9711.0",
    "gn:admin4_code":"97134.0",
    "gn:asciiname":"Bel-Air",
    "gn:country_code":"GP",
    "gn:dem":55,
    "gn:feature_class":"P",
    "gn:feature_code":"PPL",
    "gn:name":"Bel-Air",
    "gn:population":0,
    "gn:timezone":"America/Guadeloupe",
    "iso:country":"GP",
    "name:fra_x_preferred":[
        "Bel-Air"
    ],
    "name:und_x_variant":[
        "Bel Air"
    ],
    "wof:name":"Bel-Air",
    "wof:placetype":"locality"
},
  "geometry": {"coordinates":[-61.75741,16.06981],"type":"Point"}
}