{
  "type": "Feature",
  "properties": {
    "gn:admin1_code":"00",
    "gn:asciiname":"Belle Place",
    "gn:country_code":"GP",
    "gn:dem":31,
    "gn:feature_class":"P",
    "gn:feature_code":"PPLL",
    "gn:name":"Belle Place",
    "gn:population":0,
    "gn:timezone":"America/Guadeloupe",
    "iso:country":"GP",
    "name:fra_x_preferred":[
        "Belle Place"
    ],
    "wof:name":"Belle Place",
    "wof:placetype":"locality"
},
  "geometry": {"coordinates":[-61.24846,16.2705],"type":"Point"}
}