{
  "type": "Feature",
  "properties": {
    "gn:admin1_code":"00",
    "gn:asciiname":"Titon",
    "gn:country_code":"GP",
    "gn:dem":52,
    "gn:feature_class":"P",
    "gn:feature_code":"PPL",
    "gn:name":"Titon",
    "gn:population":0,
    "gn:timezone":"America/Guadeloupe",
    "iso:country":"GP",
    "name:fra_x_preferred":[
        "Titon"
    ],
    "wof:name":"Titon",
    "wof:placetype":"locality"
},
  "geometry": {"coordinates":[-61.48724,16.22062],"type":"Point"}
}