{
  "type": "Feature",
  "properties": {
    "gn:admin1_code":"00",
    "gn:asciiname":"Clerange",
    "gn:country_code":"GP",
    "gn:dem":148,
    "gn:feature_class":"P",
    "gn:feature_code":"PPL",
    "gn:name":"Cl\u00e9range",
    "gn:population":0,
    "gn:timezone":"America/Guadeloupe",
    "iso:country":"GP",
    "name:fra_x_preferred":[
        "Cl\u00e9range"
    ],
    "wof:name":"Clerange",
    "wof:placetype":"locality"
},
  "geometry": {"coordinates":[-61.26726,15.90732],"type":"Point"}
}