{
  "type": "Feature",
  "properties": {
    "gn:country":"GP",
    "gn:fcode":"ADM4",
    "gn:pop":7115,
    "iso:country":"GP",
    "name:ara_x_preferred":[
        "\u0628\u0648\u0627\u0646\u062a-\u0646\u0648\u0627\u0631"
    ],
    "name:ukr_x_preferred":[
        "\u041f\u0443\u0435\u043d\u0442-\u041d\u0443\u0430\u0440"
    ],
    "qs:name":"Pointe-Noire",
    "qs:photos_9r":0,
    "qs:photos_sr":0,
    "qs:pop_sr":"5",
    "wd:wordcount":1278,
    "wof:name":"Pointe-Noire",
    "wof:placetype":"localadmin",
    "wof:population":7115
},
  "geometry": {"coordinates":[-61.78333,16.23333],"type":"Point"}
}