{
  "type": "Feature",
  "properties": {
    "gn:admin1_code":"00",
    "gn:asciiname":"Saint-Charles",
    "gn:country_code":"GP",
    "gn:dem":59,
    "gn:feature_class":"P",
    "gn:feature_code":"PPL",
    "gn:name":"Saint-Charles",
    "gn:population":0,
    "gn:timezone":"America/Guadeloupe",
    "iso:country":"GP",
    "name:fra_x_preferred":[
        "Saint-Charles"
    ],
    "wof:name":"Saint-Charles",
    "wof:placetype":"locality"
},
  "geometry": {"coordinates":[-61.32475,16.26959],"type":"Point"}
}