{
  "type": "Feature",
  "properties": {
    "gn:admin1_code":"GP",
    "gn:admin2_code":"971",
    "gn:admin3_code":"9712.0",
    "gn:admin4_code":"97117.0",
    "gn:asciiname":"L'Anglais",
    "gn:country_code":"GP",
    "gn:dem":52,
    "gn:feature_class":"P",
    "gn:feature_code":"PPL",
    "gn:name":"L\u2019Anglais",
    "gn:population":0,
    "gn:timezone":"America/Guadeloupe",
    "iso:country":"GP",
    "name:fra_x_preferred":[
        "L\u2019Anglais"
    ],
    "name:und_x_variant":[
        "Lahglois",
        "Langlois"
    ],
    "wof:name":"L'Anglais",
    "wof:placetype":"locality"
},
  "geometry": {"coordinates":[-61.38661,16.33844],"type":"Point"}
}