{
  "type": "Feature",
  "properties": {
    "gn:admin1_code":"00",
    "gn:asciiname":"Mont d'Or",
    "gn:country_code":"GP",
    "gn:dem":590,
    "gn:feature_class":"P",
    "gn:feature_code":"PPL",
    "gn:name":"Mont d\u2019Or",
    "gn:population":0,
    "gn:timezone":"America/Guadeloupe",
    "iso:country":"GP",
    "name:ceb_x_preferred":[
        "Mont d'Or"
    ],
    "name:deu_x_preferred":[
        "Mont d\u2019Or"
    ],
    "name:fra_x_preferred":[
        "Mont d\u2019Or"
    ],
    "name:fra_x_variant":[
        "Mont d'Or"
    ],
    "name:nld_x_preferred":[
        "Mont d'Or"
    ],
    "name:swe_x_preferred":[
        "Mont d'Or"
    ],
    "wof:name":"Mont d'Or",
    "wof:placetype":"locality"
},
  "geometry": {"coordinates":[-61.71508000000001,16.05732],"type":"Point"}
}