{
  "type": "Feature",
  "properties": {
    "gn:admin1_code":"00",
    "gn:asciiname":"Delisle",
    "gn:country_code":"GP",
    "gn:dem":46,
    "gn:feature_class":"P",
    "gn:feature_code":"PPL",
    "gn:name":"Delisle",
    "gn:population":0,
    "gn:timezone":"America/Guadeloupe",
    "iso:country":"GP",
    "name:deu_x_preferred":[
        "Delisle"
    ],
    "name:fra_x_preferred":[
        "Delisle"
    ],
    "name:frr_x_preferred":[
        "Delisle"
    ],
    "name:heb_x_preferred":[
        "\u05d3\u05d4 \u05dc\u05d9\u05dc"
    ],
    "name:ita_x_preferred":[
        "Delisle"
    ],
    "name:nld_x_preferred":[
        "Delisle"
    ],
    "name:rus_x_preferred":[
        "\u0414\u0435\u043b\u0438\u043b\u044c"
    ],
    "name:spa_x_preferred":[
        "Delisle"
    ],
    "name:swe_x_preferred":[
        "Delisle"
    ],
    "wof:name":"Delisle",
    "wof:placetype":"locality"
},
  "geometry": {"coordinates":[-61.44667,16.36435],"type":"Point"}
}