{
  "type": "Feature",
  "properties": {
    "gn:admin1_code":"00",
    "gn:asciiname":"Delisle",
    "gn:country_code":"GP",
    "gn:dem":46,
    "gn:feature_class":"P",
    "gn:feature_code":"PPL",
    "gn:name":"Delisle",
    "gn:population":0,
    "gn:timezone":"America/Guadeloupe",
    "iso:country":"GP",
    "name:fra_x_preferred":[
        "Delisle"
    ],
    "wof:name":"Delisle",
    "wof:placetype":"locality"
},
  "geometry": {"coordinates":[-61.44667,16.36435],"type":"Point"}
}