{
  "type": "Feature",
  "properties": {
    "gn:admin1_code":"00",
    "gn:asciiname":"Comperou",
    "gn:country_code":"GP",
    "gn:dem":145,
    "gn:feature_class":"P",
    "gn:feature_code":"PPL",
    "gn:name":"Comp\u00e9rou",
    "gn:population":0,
    "gn:timezone":"America/Guadeloupe",
    "iso:country":"GP",
    "name:fra_x_preferred":[
        "Comp\u00e9rou"
    ],
    "wof:name":"Comperou",
    "wof:placetype":"locality"
},
  "geometry": {"coordinates":[-61.64547,16.20582000000001],"type":"Point"}
}