{
  "type": "Feature",
  "properties": {
    "gn:admin1_code":"00",
    "gn:asciiname":"Chantilly",
    "gn:country_code":"GP",
    "gn:dem":37,
    "gn:feature_class":"P",
    "gn:feature_code":"PPL",
    "gn:name":"Chantilly",
    "gn:population":0,
    "gn:timezone":"America/Guadeloupe",
    "iso:country":"GP",
    "name:ceb_x_preferred":[
        "Chantilly"
    ],
    "name:ces_x_preferred":[
        "Chantilly"
    ],
    "name:deu_x_preferred":[
        "Chantilly"
    ],
    "name:ell_x_preferred":[
        "\u03a3\u03b1\u03bd\u03c4\u03b9\u03b3\u03af"
    ],
    "name:fra_x_preferred":[
        "Chantilly"
    ],
    "name:heb_x_preferred":[
        "\u05e9\u05e0\u05d8\u05d9\u05dc\u05d9"
    ],
    "name:nld_x_preferred":[
        "Chantilly"
    ],
    "name:por_x_preferred":[
        "Chantilly"
    ],
    "name:rus_x_preferred":[
        "\u0428\u0430\u043d\u0442\u0438\u0439\u0438"
    ],
    "name:slk_x_preferred":[
        "Chantilly"
    ],
    "name:spa_x_preferred":[
        "Chantilly"
    ],
    "name:vol_x_preferred":[
        "Chantilly"
    ],
    "wof:name":"Chantilly",
    "wof:placetype":"locality"
},
  "geometry": {"coordinates":[-61.61697,16.23593],"type":"Point"}
}