{
  "type": "Feature",
  "properties": {
    "gn:admin1_code":"00",
    "gn:asciiname":"Chantilly",
    "gn:country_code":"GP",
    "gn:dem":37,
    "gn:feature_class":"P",
    "gn:feature_code":"PPL",
    "gn:name":"Chantilly",
    "gn:population":0,
    "gn:timezone":"America/Guadeloupe",
    "iso:country":"GP",
    "name:fra_x_preferred":[
        "Chantilly"
    ],
    "wof:name":"Chantilly",
    "wof:placetype":"locality"
},
  "geometry": {"coordinates":[-61.61697,16.23593],"type":"Point"}
}