{
  "type": "Feature",
  "properties": {
    "gn:admin1_code":"00",
    "gn:asciiname":"Martin",
    "gn:country_code":"GP",
    "gn:dem":57,
    "gn:feature_class":"P",
    "gn:feature_code":"PPL",
    "gn:name":"Martin",
    "gn:population":0,
    "gn:timezone":"America/Guadeloupe",
    "iso:country":"GP",
    "name:fra_x_preferred":[
        "Martin"
    ],
    "wof:name":"Martin",
    "wof:placetype":"locality"
},
  "geometry": {"coordinates":[-61.2539,15.98476],"type":"Point"}
}