{
  "type": "Feature",
  "properties": {
    "gn:admin1_code":"00",
    "gn:asciiname":"Chauvel",
    "gn:country_code":"GP",
    "gn:dem":26,
    "gn:feature_class":"P",
    "gn:feature_code":"PPL",
    "gn:name":"Chauvel",
    "gn:population":0,
    "gn:timezone":"America/Guadeloupe",
    "iso:country":"GP",
    "name:fra_x_preferred":[
        "Chauvel"
    ],
    "wof:name":"Chauvel",
    "wof:placetype":"locality"
},
  "geometry": {"coordinates":[-61.51635,16.23961],"type":"Point"}
}