{
  "type": "Feature",
  "properties": {
    "gn:admin1_code":"00",
    "gn:asciiname":"Christophe",
    "gn:country_code":"GP",
    "gn:dem":25,
    "gn:feature_class":"P",
    "gn:feature_code":"PPL",
    "gn:name":"Christophe",
    "gn:population":0,
    "gn:timezone":"America/Guadeloupe",
    "iso:country":"GP",
    "name:deu_x_preferred":[
        "Christophe"
    ],
    "name:fra_x_preferred":[
        "Christophe"
    ],
    "name:heb_x_preferred":[
        "\u05db\u05e8\u05d9\u05e1\u05d8\u05d5\u05e3"
    ],
    "name:nld_x_preferred":[
        "Christophe"
    ],
    "name:rus_x_preferred":[
        "\u041a\u0440\u0438\u0441\u0442\u043e\u0444"
    ],
    "name:spa_x_preferred":[
        "Christophe"
    ],
    "wof:name":"Christophe",
    "wof:placetype":"locality"
},
  "geometry": {"coordinates":[-61.57182,16.11267999999999],"type":"Point"}
}