{
  "type": "Feature",
  "properties": {
    "gn:admin1_code":"00",
    "gn:asciiname":"Duvaliere",
    "gn:country_code":"GP",
    "gn:dem":39,
    "gn:feature_class":"P",
    "gn:feature_code":"PPLL",
    "gn:name":"Duvali\u00e8re",
    "gn:population":0,
    "gn:timezone":"America/Guadeloupe",
    "iso:country":"GP",
    "name:fra_x_preferred":[
        "Duvali\u00e8re"
    ],
    "name:fra_x_variant":[
        "Goyon"
    ],
    "wof:name":"Duvaliere",
    "wof:placetype":"locality"
},
  "geometry": {"coordinates":[-61.4408,16.41078],"type":"Point"}
}