{
  "type": "Feature",
  "properties": {
    "gn:admin1_code":"GP",
    "gn:admin2_code":"971",
    "gn:admin3_code":"9711.0",
    "gn:admin4_code":"97132.0",
    "gn:asciiname":"Saint-Gilles",
    "gn:country_code":"GP",
    "gn:dem":248,
    "gn:feature_class":"P",
    "gn:feature_code":"PPL",
    "gn:name":"Saint-Gilles",
    "gn:population":0,
    "gn:timezone":"America/Guadeloupe",
    "iso:country":"GP",
    "wof:name":"Saint-Gilles",
    "wof:placetype":"locality"
},
  "geometry": {"coordinates":[-61.63333000000001,15.98333],"type":"Point"}
}