{
  "type": "Feature",
  "properties": {
    "gn:admin1_code":"GP",
    "gn:admin2_code":"971",
    "gn:admin3_code":"9711.0",
    "gn:admin4_code":"97132.0",
    "gn:asciiname":"Saint-Gilles",
    "gn:country_code":"GP",
    "gn:dem":248,
    "gn:feature_class":"P",
    "gn:feature_code":"PPL",
    "gn:name":"Saint-Gilles",
    "gn:population":0,
    "gn:timezone":"America/Guadeloupe",
    "iso:country":"GP",
    "name:bre_x_preferred":[
        "Saint-Gilles"
    ],
    "name:cat_x_preferred":[
        "Saint-Gilles"
    ],
    "name:ceb_x_preferred":[
        "Saint-Gilles"
    ],
    "name:deu_x_preferred":[
        "Saint-Gilles"
    ],
    "name:fin_x_preferred":[
        "Saint-Gilles"
    ],
    "name:fra_x_preferred":[
        "Saint-Gilles"
    ],
    "name:ita_x_preferred":[
        "Saint-Gilles"
    ],
    "name:jpn_x_preferred":[
        "\u30b5\u30f3\uff1d\u30b8\u30eb"
    ],
    "name:ltz_x_preferred":[
        "Saint-Gilles"
    ],
    "name:nds_x_preferred":[
        "Saint-Gilles"
    ],
    "name:nld_x_preferred":[
        "Saint-Gilles"
    ],
    "name:oci_x_preferred":[
        "Saint-Gilles"
    ],
    "name:pms_x_preferred":[
        "Saint-Gilles"
    ],
    "name:pol_x_preferred":[
        "Saint-Gilles"
    ],
    "name:por_x_preferred":[
        "Saint-Gilles"
    ],
    "name:rus_x_preferred":[
        "\u0421\u0435\u043d-\u0416\u0438\u043b\u044c"
    ],
    "name:sco_x_preferred":[
        "Saint-Gilles"
    ],
    "name:spa_x_preferred":[
        "Saint-Gilles"
    ],
    "name:swe_x_preferred":[
        "Saint-Gilles"
    ],
    "name:ukr_x_preferred":[
        "\u0421\u0435\u043d-\u0416\u0438\u043b\u044c"
    ],
    "wof:name":"Saint-Gilles",
    "wof:placetype":"locality"
},
  "geometry": {"coordinates":[-61.63333000000001,15.98333],"type":"Point"}
}