{
  "type": "Feature",
  "properties": {
    "gn:admin1_code":"00",
    "gn:asciiname":"Blanchard",
    "gn:country_code":"GP",
    "gn:dem":38,
    "gn:feature_class":"P",
    "gn:feature_code":"PPL",
    "gn:name":"Blanchard",
    "gn:population":0,
    "gn:timezone":"America/Guadeloupe",
    "iso:country":"GP",
    "name:fra_x_preferred":[
        "Blanchard"
    ],
    "wof:name":"Blanchard",
    "wof:placetype":"locality"
},
  "geometry": {"coordinates":[-61.4663,16.27685],"type":"Point"}
}