{
  "type": "Feature",
  "properties": {
    "gn:admin1_code":"GP",
    "gn:admin2_code":"971",
    "gn:admin3_code":"9712.0",
    "gn:admin4_code":"97117.0",
    "gn:asciiname":"Coignet",
    "gn:country_code":"GP",
    "gn:dem":50,
    "gn:feature_class":"P",
    "gn:feature_code":"PPL",
    "gn:name":"Coignet",
    "gn:population":0,
    "gn:timezone":"America/Guadeloupe",
    "iso:country":"GP",
    "wof:name":"Coignet",
    "wof:placetype":"locality"
},
  "geometry": {"coordinates":[-61.41667,16.36667000000001],"type":"Point"}
}