{
  "type": "Feature",
  "properties": {
    "gn:admin1_code":"00",
    "gn:asciiname":"Les Trois Chemins Saint-Guillaume",
    "gn:country_code":"GP",
    "gn:dem":43,
    "gn:feature_class":"P",
    "gn:feature_code":"PPLL",
    "gn:name":"Les Trois Chemins Saint-Guillaume",
    "gn:population":0,
    "gn:timezone":"America/Guadeloupe",
    "iso:country":"GP",
    "name:fra_x_preferred":[
        "Les Trois Chemins Saint-Guillaume"
    ],
    "wof:name":"Les Trois Chemins Saint-Guillaume",
    "wof:placetype":"locality"
},
  "geometry": {"coordinates":[-61.39057,16.28403],"type":"Point"}
}