{
  "type": "Feature",
  "properties": {
    "gn:admin1_code":"00",
    "gn:asciiname":"Jean-Baptiste",
    "gn:country_code":"GP",
    "gn:dem":17,
    "gn:feature_class":"P",
    "gn:feature_code":"PPL",
    "gn:name":"Jean-Baptiste",
    "gn:population":0,
    "gn:timezone":"America/Guadeloupe",
    "iso:country":"GP",
    "name:fra_x_preferred":[
        "Jean-Baptiste"
    ],
    "wof:name":"Jean-Baptiste",
    "wof:placetype":"locality"
},
  "geometry": {"coordinates":[-61.47224,16.22354],"type":"Point"}
}