{
  "type": "Feature",
  "properties": {
    "gn:admin1_code":"00",
    "gn:asciiname":"Jean-Baptiste",
    "gn:country_code":"GP",
    "gn:dem":17,
    "gn:feature_class":"P",
    "gn:feature_code":"PPL",
    "gn:name":"Jean-Baptiste",
    "gn:population":0,
    "gn:timezone":"America/Guadeloupe",
    "iso:country":"GP",
    "name:fra_x_preferred":[
        "Jean-Baptiste"
    ],
    "name:jpn_x_preferred":[
        "\u30b8\u30e3\u30f3\uff1d\u30d0\u30c6\u30a3\u30b9\u30c8"
    ],
    "name:kor_x_preferred":[
        "\uc7a5\ubc14\ud2f0\uc2a4\ud2b8"
    ],
    "name:nld_x_preferred":[
        "Jean-Baptiste"
    ],
    "name:nno_x_preferred":[
        "Jean-Baptiste"
    ],
    "name:rus_x_preferred":[
        "\u0416\u0430\u043d-\u0411\u0430\u0442\u0438\u0441\u0442"
    ],
    "name:spa_x_preferred":[
        "Jean-Baptiste"
    ],
    "wof:name":"Jean-Baptiste",
    "wof:placetype":"locality"
},
  "geometry": {"coordinates":[-61.47224,16.22354],"type":"Point"}
}