{
  "type": "Feature",
  "properties": {
    "gn:admin1_code":"00",
    "gn:asciiname":"Rollier",
    "gn:country_code":"GP",
    "gn:dem":93,
    "gn:feature_class":"P",
    "gn:feature_code":"PPL",
    "gn:name":"Rollier",
    "gn:population":0,
    "gn:timezone":"America/Guadeloupe",
    "iso:country":"GP",
    "name:fra_x_preferred":[
        "Rollier"
    ],
    "wof:name":"Rollier",
    "wof:placetype":"locality"
},
  "geometry": {"coordinates":[-61.76551,16.13163],"type":"Point"}
}