{
  "type": "Feature",
  "properties": {
    "gn:admin1_code":"GP",
    "gn:admin2_code":"971",
    "gn:admin3_code":"9712.0",
    "gn:admin4_code":"97128.0",
    "gn:asciiname":"Fouche",
    "gn:country_code":"GP",
    "gn:dem":96,
    "gn:feature_class":"P",
    "gn:feature_code":"PPL",
    "gn:name":"Fouch\u00e9",
    "gn:population":0,
    "gn:timezone":"America/Guadeloupe",
    "iso:country":"GP",
    "name:fra_x_preferred":[
        "Fouch\u00e9"
    ],
    "wof:name":"Fouche",
    "wof:placetype":"locality"
},
  "geometry": {"coordinates":[-61.40281,16.24318],"type":"Point"}
}