{
  "type": "Feature",
  "properties": {
    "gn:admin1_code":"00",
    "gn:asciiname":"Grand Riviere",
    "gn:country_code":"GP",
    "gn:dem":19,
    "gn:feature_class":"P",
    "gn:feature_code":"PPL",
    "gn:name":"Grand Rivi\u00e8re",
    "gn:population":0,
    "gn:timezone":"America/Guadeloupe",
    "iso:country":"GP",
    "name:fra_x_preferred":[
        "Grand Rivi\u00e8re"
    ],
    "wof:name":"Grand Riviere",
    "wof:placetype":"locality"
},
  "geometry": {"coordinates":[-61.56289,16.05744],"type":"Point"}
}