{
  "type": "Feature",
  "properties": {
    "gn:admin1_code":"00",
    "gn:asciiname":"Bois Plaisir",
    "gn:country_code":"GP",
    "gn:dem":116,
    "gn:feature_class":"P",
    "gn:feature_code":"PPL",
    "gn:name":"Bois Plaisir",
    "gn:population":0,
    "gn:timezone":"America/Guadeloupe",
    "iso:country":"GP",
    "name:fra_x_preferred":[
        "Bois Plaisir"
    ],
    "wof:name":"Bois Plaisir",
    "wof:placetype":"locality"
},
  "geometry": {"coordinates":[-61.41796,16.26334],"type":"Point"}
}