{
  "type": "Feature",
  "properties": {
    "gn:admin1_code":"00",
    "gn:asciiname":"Gilles Arcon",
    "gn:country_code":"GP",
    "gn:dem":53,
    "gn:feature_class":"P",
    "gn:feature_code":"PPL",
    "gn:name":"Gilles Ar\u00e7on",
    "gn:population":0,
    "gn:timezone":"America/Guadeloupe",
    "iso:country":"GP",
    "name:fra_x_preferred":[
        "Gilles Ar\u00e7on"
    ],
    "wof:name":"Gilles Arcon",
    "wof:placetype":"locality"
},
  "geometry": {"coordinates":[-61.41476,16.30357],"type":"Point"}
}