{
  "type": "Feature",
  "properties": {
    "gn:admin1_code":"00",
    "gn:asciiname":"Liard Saint-Robert",
    "gn:country_code":"GP",
    "gn:dem":98,
    "gn:feature_class":"P",
    "gn:feature_code":"PPL",
    "gn:name":"Liard Saint-Robert",
    "gn:population":0,
    "gn:timezone":"America/Guadeloupe",
    "iso:country":"GP",
    "name:fra_x_preferred":[
        "Liard Saint-Robert"
    ],
    "wof:name":"Liard Saint-Robert",
    "wof:placetype":"locality"
},
  "geometry": {"coordinates":[-61.40938000000001,16.2741],"type":"Point"}
}