{
  "type": "Feature",
  "properties": {
    "gn:admin1_code":"00",
    "gn:asciiname":"Michaux",
    "gn:country_code":"GP",
    "gn:dem":116,
    "gn:feature_class":"P",
    "gn:feature_code":"PPL",
    "gn:name":"Michaux",
    "gn:population":0,
    "gn:timezone":"America/Guadeloupe",
    "iso:country":"GP",
    "name:cat_x_preferred":[
        "Michaux"
    ],
    "name:deu_x_preferred":[
        "Michaux"
    ],
    "name:fra_x_preferred":[
        "Michaux"
    ],
    "name:jpn_x_preferred":[
        "\u30df\u30b7\u30e7\u30fc"
    ],
    "name:pol_x_preferred":[
        "Michaux"
    ],
    "name:rus_x_preferred":[
        "\u041c\u0438\u0448\u043e"
    ],
    "name:ukr_x_preferred":[
        "\u041c\u0456\u0448\u043e"
    ],
    "wof:name":"Michaux",
    "wof:placetype":"locality"
},
  "geometry": {"coordinates":[-61.44381,16.23398],"type":"Point"}
}