{
  "type": "Feature",
  "properties": {
    "gn:admin1_code":"00",
    "gn:asciiname":"Pinaud",
    "gn:country_code":"GP",
    "gn:dem":50,
    "gn:feature_class":"P",
    "gn:feature_code":"PPL",
    "gn:name":"Pinaud",
    "gn:population":0,
    "gn:timezone":"America/Guadeloupe",
    "iso:country":"GP",
    "name:deu_x_preferred":[
        "Pinaud"
    ],
    "name:fra_x_preferred":[
        "Pinaud"
    ],
    "wof:name":"Pinaud",
    "wof:placetype":"locality"
},
  "geometry": {"coordinates":[-61.7707,16.33819],"type":"Point"}
}