{
  "type": "Feature",
  "properties": {
    "gn:admin1_code":"00",
    "gn:asciiname":"Pafory",
    "gn:country_code":"GP",
    "gn:dem":60,
    "gn:feature_class":"P",
    "gn:feature_code":"PPL",
    "gn:name":"Pafory",
    "gn:population":0,
    "gn:timezone":"America/Guadeloupe",
    "iso:country":"GP",
    "name:fra_x_preferred":[
        "Pafory"
    ],
    "wof:name":"Pafory",
    "wof:placetype":"locality"
},
  "geometry": {"coordinates":[-61.30313,15.93223],"type":"Point"}
}