{
  "type": "Feature",
  "properties": {
    "gn:admin1_code":"00",
    "gn:asciiname":"La Deboulee",
    "gn:country_code":"GP",
    "gn:dem":108,
    "gn:feature_class":"P",
    "gn:feature_code":"PPL",
    "gn:name":"La D\u00e9boul\u00e9e",
    "gn:population":0,
    "gn:timezone":"America/Guadeloupe",
    "iso:country":"GP",
    "name:fra_x_preferred":[
        "La D\u00e9boul\u00e9e"
    ],
    "wof:name":"La Deboulee",
    "wof:placetype":"locality"
},
  "geometry": {"coordinates":[-61.69866,16.26553],"type":"Point"}
}