{
  "type": "Feature",
  "properties": {
    "gn:admin1_code":"00",
    "gn:asciiname":"Nord-Ouest",
    "gn:country_code":"GP",
    "gn:dem":27,
    "gn:feature_class":"P",
    "gn:feature_code":"PPL",
    "gn:name":"Nord-Ouest",
    "gn:population":0,
    "gn:timezone":"America/Guadeloupe",
    "iso:country":"GP",
    "name:fra_x_preferred":[
        "Nord-Ouest"
    ],
    "wof:name":"Nord-Ouest",
    "wof:placetype":"locality"
},
  "geometry": {"coordinates":[-61.36834,16.30015],"type":"Point"}
}