{
  "type": "Feature",
  "properties": {
    "gn:admin1_code":"00",
    "gn:asciiname":"Nord-Ouest",
    "gn:country_code":"GP",
    "gn:dem":27,
    "gn:feature_class":"P",
    "gn:feature_code":"PPL",
    "gn:name":"Nord-Ouest",
    "gn:population":0,
    "gn:timezone":"America/Guadeloupe",
    "iso:country":"GP",
    "name:bjn_x_preferred":[
        "Barat laut"
    ],
    "name:ceb_x_preferred":[
        "Nord-Ouest"
    ],
    "name:deu_x_preferred":[
        "Nord-Ouest"
    ],
    "name:fra_x_preferred":[
        "Nord-Ouest"
    ],
    "name:fra_x_variant":[
        "Nord-ouest"
    ],
    "name:heb_x_preferred":[
        "\u05e0\u05d5\u05e8\u05d3-\u05d0\u05d5\u05e1\u05d8"
    ],
    "name:hun_x_preferred":[
        "Nord-Ouest"
    ],
    "name:nld_x_preferred":[
        "Nord-Ouest"
    ],
    "name:swe_x_preferred":[
        "Nord-Ouest"
    ],
    "wof:name":"Nord-Ouest",
    "wof:placetype":"locality"
},
  "geometry": {"coordinates":[-61.36834,16.30015],"type":"Point"}
}