{
  "type": "Feature",
  "properties": {
    "gn:admin1_code":"00",
    "gn:asciiname":"Le Bouchu",
    "gn:country_code":"GP",
    "gn:dem":22,
    "gn:feature_class":"P",
    "gn:feature_code":"PPL",
    "gn:name":"Le Bouchu",
    "gn:population":0,
    "gn:timezone":"America/Guadeloupe",
    "iso:country":"GP",
    "name:fra_x_preferred":[
        "Le Bouchu"
    ],
    "wof:name":"Le Bouchu",
    "wof:placetype":"locality"
},
  "geometry": {"coordinates":[-61.76275,16.06512],"type":"Point"}
}