{
  "type": "Feature",
  "properties": {
    "gn:admin1_code":"00",
    "gn:asciiname":"Bois Gris",
    "gn:country_code":"GP",
    "gn:dem":113,
    "gn:feature_class":"P",
    "gn:feature_code":"PPLL",
    "gn:name":"Bois Gris",
    "gn:population":0,
    "gn:timezone":"America/Guadeloupe",
    "iso:country":"GP",
    "name:fra_x_preferred":[
        "Bois Gris"
    ],
    "wof:name":"Bois Gris",
    "wof:placetype":"locality"
},
  "geometry": {"coordinates":[-61.64861,16.18264],"type":"Point"}
}