{
  "type": "Feature",
  "properties": {
    "gn:admin1_code":"00",
    "gn:asciiname":"Bagatelle",
    "gn:country_code":"GP",
    "gn:dem":508,
    "gn:feature_class":"P",
    "gn:feature_code":"PPL",
    "gn:name":"Bagatelle",
    "gn:population":0,
    "gn:timezone":"America/Guadeloupe",
    "iso:country":"GP",
    "name:fra_x_preferred":[
        "Bagatelle"
    ],
    "wof:name":"Bagatelle",
    "wof:placetype":"locality"
},
  "geometry": {"coordinates":[-61.68676,16.01757000000001],"type":"Point"}
}