{
  "type": "Feature",
  "properties": {
    "gn:admin1_code":"00",
    "gn:asciiname":"Sarlassone",
    "gn:country_code":"GP",
    "gn:dem":5,
    "gn:feature_class":"P",
    "gn:feature_code":"PPL",
    "gn:name":"Sarlassone",
    "gn:population":0,
    "gn:timezone":"America/Guadeloupe",
    "iso:country":"GP",
    "name:fra_x_preferred":[
        "Sarlassone"
    ],
    "wof:name":"Sarlassone",
    "wof:placetype":"locality"
},
  "geometry": {"coordinates":[-61.55889000000001,16.05105],"type":"Point"}
}