{
  "type": "Feature",
  "properties": {
    "gn:admin1_code":"00",
    "gn:asciiname":"Dain",
    "gn:country_code":"GP",
    "gn:dem":268,
    "gn:feature_class":"P",
    "gn:feature_code":"PPL",
    "gn:name":"Dain",
    "gn:population":0,
    "gn:timezone":"America/Guadeloupe",
    "iso:country":"GP",
    "name:fra_x_preferred":[
        "Dain"
    ],
    "wof:name":"Dain",
    "wof:placetype":"locality"
},
  "geometry": {"coordinates":[-61.70853,16.0107],"type":"Point"}
}