{
  "type": "Feature",
  "properties": {
    "gn:admin1_code":"00",
    "gn:asciiname":"Rougeole",
    "gn:country_code":"GP",
    "gn:dem":24,
    "gn:feature_class":"P",
    "gn:feature_code":"PPL",
    "gn:name":"Rougeole",
    "gn:population":0,
    "gn:timezone":"America/Guadeloupe",
    "iso:country":"GP",
    "name:fra_x_preferred":[
        "Rougeole"
    ],
    "wof:name":"Rougeole",
    "wof:placetype":"locality"
},
  "geometry": {"coordinates":[-61.4557,16.36025],"type":"Point"}
}