{
  "type": "Feature",
  "properties": {
    "gn:admin1_code":"GP",
    "gn:admin2_code":"971",
    "gn:admin3_code":"9712.0",
    "gn:admin4_code":"97122.0",
    "gn:asciiname":"Brument",
    "gn:country_code":"GP",
    "gn:dem":22,
    "gn:feature_class":"P",
    "gn:feature_code":"PPL",
    "gn:name":"Brument",
    "gn:population":0,
    "gn:timezone":"America/Guadeloupe",
    "iso:country":"GP",
    "name:und_x_variant":[
        "Bruman",
        "Brument"
    ],
    "wof:name":"Brument",
    "wof:placetype":"locality"
},
  "geometry": {"coordinates":[-61.50568000000001,16.41566],"type":"Point"}
}