{
  "type": "Feature",
  "properties": {
    "gn:admin1_code":"00",
    "gn:asciiname":"Cambourg",
    "gn:country_code":"GP",
    "gn:dem":96,
    "gn:feature_class":"P",
    "gn:feature_code":"PPL",
    "gn:name":"Cambourg",
    "gn:population":0,
    "gn:timezone":"America/Guadeloupe",
    "iso:country":"GP",
    "name:fra_x_preferred":[
        "Cambourg"
    ],
    "wof:name":"Cambourg",
    "wof:placetype":"locality"
},
  "geometry": {"coordinates":[-61.41597,16.27938],"type":"Point"}
}