{
  "type": "Feature",
  "properties": {
    "gn:country":"GP",
    "gn:fcode":"ADM4",
    "gn:pop":8243,
    "iso:country":"GP",
    "qs:name":"Petit-Canal",
    "qs:photos_9r":0,
    "qs:photos_sr":0,
    "qs:pop_sr":"5",
    "wd:wordcount":25,
    "wof:name":"Petit-Canal",
    "wof:placetype":"localadmin",
    "wof:population":8243
},
  "geometry": {"coordinates":[-61.48333,16.38333],"type":"Point"}
}