{
  "type": "Feature",
  "properties": {
    "gn:admin1_code":"00",
    "gn:asciiname":"Papin",
    "gn:country_code":"GP",
    "gn:dem":113,
    "gn:feature_class":"P",
    "gn:feature_code":"PPL",
    "gn:name":"Papin",
    "gn:population":0,
    "gn:timezone":"America/Guadeloupe",
    "iso:country":"GP",
    "name:fra_x_preferred":[
        "Papin"
    ],
    "wof:name":"Papin",
    "wof:placetype":"locality"
},
  "geometry": {"coordinates":[-61.64214000000001,16.21104],"type":"Point"}
}