{
  "type": "Feature",
  "properties": {
    "gn:admin1_code":"00",
    "gn:asciiname":"Moleon",
    "gn:country_code":"GP",
    "gn:dem":306,
    "gn:feature_class":"P",
    "gn:feature_code":"PPL",
    "gn:name":"Mol\u00e9on",
    "gn:population":0,
    "gn:timezone":"America/Guadeloupe",
    "iso:country":"GP",
    "name:fra_x_preferred":[
        "Mol\u00e9on"
    ],
    "wof:name":"Moleon",
    "wof:placetype":"locality"
},
  "geometry": {"coordinates":[-61.70133000000001,16.01165],"type":"Point"}
}