{
  "type": "Feature",
  "properties": {
    "gn:admin1_code":"00",
    "gn:asciiname":"Bourgelac",
    "gn:country_code":"GP",
    "gn:dem":188,
    "gn:feature_class":"P",
    "gn:feature_code":"PPL",
    "gn:name":"Bourgelac",
    "gn:population":0,
    "gn:timezone":"America/Guadeloupe",
    "iso:country":"GP",
    "name:fra_x_preferred":[
        "Bourgelac"
    ],
    "wof:name":"Bourgelac",
    "wof:placetype":"locality"
},
  "geometry": {"coordinates":[-61.22584000000001,15.9548],"type":"Point"}
}