{
  "type": "Feature",
  "properties": {
    "gn:admin1_code":"00",
    "gn:asciiname":"Le Mouillage",
    "gn:country_code":"GP",
    "gn:dem":11,
    "gn:feature_class":"P",
    "gn:feature_code":"PPL",
    "gn:name":"Le Mouillage",
    "gn:population":0,
    "gn:timezone":"America/Guadeloupe",
    "iso:country":"GP",
    "name:fra_x_preferred":[
        "Le Mouillage"
    ],
    "wof:name":"Le Mouillage",
    "wof:placetype":"locality"
},
  "geometry": {"coordinates":[-61.58175,15.86927],"type":"Point"}
}