{
  "type": "Feature",
  "properties": {
    "gn:admin1_code":"00",
    "gn:asciiname":"Belair-Leborgne",
    "gn:country_code":"GP",
    "gn:dem":32,
    "gn:feature_class":"P",
    "gn:feature_code":"PPLL",
    "gn:name":"Belair-Leborgne",
    "gn:population":0,
    "gn:timezone":"America/Guadeloupe",
    "iso:country":"GP",
    "name:fra_x_preferred":[
        "Belair-Leborgne"
    ],
    "wof:name":"Belair-Leborgne",
    "wof:placetype":"locality"
},
  "geometry": {"coordinates":[-61.46738000000001,16.41881],"type":"Point"}
}