{
  "type": "Feature",
  "properties": {
    "gn:admin1_code":"GP",
    "gn:admin2_code":"971",
    "gn:admin3_code":"9712.0",
    "gn:admin4_code":"97112.0",
    "gn:asciiname":"Ducos",
    "gn:country_code":"GP",
    "gn:dem":108,
    "gn:feature_class":"P",
    "gn:feature_code":"PPL",
    "gn:name":"Ducos",
    "gn:population":0,
    "gn:timezone":"America/Guadeloupe",
    "iso:country":"GP",
    "name:cat_x_preferred":[
        "Ducos"
    ],
    "name:ceb_x_preferred":[
        "Ducos"
    ],
    "name:deu_x_preferred":[
        "Ducos"
    ],
    "name:fra_x_preferred":[
        "Ducos"
    ],
    "name:ita_x_preferred":[
        "Ducos"
    ],
    "name:lat_x_preferred":[
        "Ducos"
    ],
    "name:msa_x_preferred":[
        "Ducos"
    ],
    "name:nld_x_preferred":[
        "Ducos"
    ],
    "name:oci_x_preferred":[
        "Ducos"
    ],
    "name:pol_x_preferred":[
        "Ducos"
    ],
    "name:slk_x_preferred":[
        "Ducos"
    ],
    "name:spa_x_preferred":[
        "Ducos"
    ],
    "name:swe_x_preferred":[
        "Ducos"
    ],
    "name:ukr_x_preferred":[
        "\u0414\u044e\u043a\u043e"
    ],
    "name:vie_x_preferred":[
        "Ducos"
    ],
    "name:war_x_preferred":[
        "Ducos"
    ],
    "wof:name":"Ducos",
    "wof:placetype":"locality"
},
  "geometry": {"coordinates":[-61.29314,15.89247],"type":"Point"}
}