{
  "type": "Feature",
  "properties": {
    "gn:admin1_code":"00",
    "gn:asciiname":"Sainte-Anne",
    "gn:country_code":"GP",
    "gn:dem":563,
    "gn:feature_class":"P",
    "gn:feature_code":"PPL",
    "gn:name":"Sainte-Anne",
    "gn:population":0,
    "gn:timezone":"America/Guadeloupe",
    "iso:country":"GP",
    "name:bre_x_preferred":[
        "Sainte-Anne"
    ],
    "name:ceb_x_preferred":[
        "Sainte-Anne"
    ],
    "name:deu_x_preferred":[
        "Sainte-Anne"
    ],
    "name:fra_x_preferred":[
        "Sainte-Anne"
    ],
    "name:ita_x_preferred":[
        "Sainte-Anne"
    ],
    "name:jpn_x_preferred":[
        "\u30b5\u30f3\u30bf\u30f3\u30cc"
    ],
    "name:nds_x_preferred":[
        "Sainte-Anne"
    ],
    "name:nld_x_preferred":[
        "Sainte-Anne"
    ],
    "name:oci_x_preferred":[
        "Sainte-Anne"
    ],
    "name:pms_x_preferred":[
        "Sainte-Anne"
    ],
    "name:pol_x_preferred":[
        "Sainte-Anne"
    ],
    "name:por_x_preferred":[
        "Sainte-Anne"
    ],
    "name:rus_x_preferred":[
        "\u0421\u0435\u043d\u0442-\u0410\u043d\u043d"
    ],
    "name:slk_x_preferred":[
        "Sainte-Anne"
    ],
    "name:spa_x_preferred":[
        "Sainte-Anne"
    ],
    "name:swe_x_preferred":[
        "Sainte-Anne"
    ],
    "name:ukr_x_preferred":[
        "\u0421\u0435\u043d\u0442-\u0410\u043d\u043d"
    ],
    "wof:name":"Sainte-Anne",
    "wof:placetype":"locality"
},
  "geometry": {"coordinates":[-61.69793000000001,16.04022],"type":"Point"}
}