{
  "type": "Feature",
  "properties": {
    "gn:admin1_code":"GP",
    "gn:admin2_code":"971",
    "gn:admin3_code":"9711.0",
    "gn:admin4_code":"97134.0",
    "gn:asciiname":"Marigot",
    "gn:country_code":"GP",
    "gn:dem":7,
    "gn:feature_class":"P",
    "gn:feature_code":"PPL",
    "gn:name":"Marigot",
    "gn:population":0,
    "gn:timezone":"America/Guadeloupe",
    "iso:country":"GP",
    "name:ceb_x_preferred":[
        "Marigot"
    ],
    "name:deu_x_preferred":[
        "Marigot"
    ],
    "name:ell_x_preferred":[
        "\u039c\u03b1\u03c1\u03b9\u03b3\u03ba\u03cc"
    ],
    "name:fra_x_preferred":[
        "Marigot"
    ],
    "name:ita_x_preferred":[
        "Marigot"
    ],
    "name:nld_x_preferred":[
        "Marigot"
    ],
    "name:pol_x_preferred":[
        "Marigot"
    ],
    "name:por_x_preferred":[
        "Marigot"
    ],
    "name:ron_x_preferred":[
        "Marigot"
    ],
    "name:spa_x_preferred":[
        "Marigot"
    ],
    "name:swe_x_preferred":[
        "Marigot"
    ],
    "name:tur_x_preferred":[
        "Marigot"
    ],
    "wof:name":"Marigot",
    "wof:placetype":"locality"
},
  "geometry": {"coordinates":[-61.76707,16.08282],"type":"Point"}
}