{
  "type": "Feature",
  "properties": {
    "gn:admin1_code":"GP",
    "gn:admin2_code":"971",
    "gn:admin3_code":"9711.0",
    "gn:admin4_code":"97134.0",
    "gn:asciiname":"Marigot",
    "gn:country_code":"GP",
    "gn:dem":7,
    "gn:feature_class":"P",
    "gn:feature_code":"PPL",
    "gn:name":"Marigot",
    "gn:population":0,
    "gn:timezone":"America/Guadeloupe",
    "iso:country":"GP",
    "name:fra_x_preferred":[
        "Marigot"
    ],
    "wof:name":"Marigot",
    "wof:placetype":"locality"
},
  "geometry": {"coordinates":[-61.76707,16.08282],"type":"Point"}
}