{
  "type": "Feature",
  "properties": {
    "gn:admin1_code":"GP",
    "gn:admin2_code":"971",
    "gn:admin3_code":"9712.0",
    "gn:admin4_code":"97125.0",
    "gn:asciiname":"Vezoux",
    "gn:country_code":"GP",
    "gn:dem":47,
    "gn:feature_class":"P",
    "gn:feature_code":"PPL",
    "gn:name":"Vezoux",
    "gn:population":0,
    "gn:timezone":"America/Guadeloupe",
    "iso:country":"GP",
    "name:und_x_variant":[
        "R\u00e9union",
        "Vezou",
        "Vezoux"
    ],
    "wof:name":"Vezoux",
    "wof:placetype":"locality"
},
  "geometry": {"coordinates":[-61.27647,16.29478],"type":"Point"}
}