{
  "type": "Feature",
  "properties": {
    "gn:admin1_code":"00",
    "gn:asciiname":"Dubec",
    "gn:country_code":"GP",
    "gn:dem":29,
    "gn:feature_class":"P",
    "gn:feature_code":"PPL",
    "gn:name":"Dubec",
    "gn:population":0,
    "gn:timezone":"America/Guadeloupe",
    "iso:country":"GP",
    "name:fra_x_preferred":[
        "Dubec"
    ],
    "wof:name":"Dubec",
    "wof:placetype":"locality"
},
  "geometry": {"coordinates":[-61.39126,16.30063],"type":"Point"}
}