{
  "type": "Feature",
  "properties": {
    "gn:admin1_code":"00",
    "gn:asciiname":"Massicri",
    "gn:country_code":"GP",
    "gn:dem":52,
    "gn:feature_class":"P",
    "gn:feature_code":"PPLL",
    "gn:name":"Massicri",
    "gn:population":0,
    "gn:timezone":"America/Guadeloupe",
    "iso:country":"GP",
    "name:fra_x_preferred":[
        "Massicri"
    ],
    "wof:name":"Massicri",
    "wof:placetype":"locality"
},
  "geometry": {"coordinates":[-61.48235,16.21876],"type":"Point"}
}