{
  "type": "Feature",
  "properties": {
    "gn:admin1_code":"00",
    "gn:asciiname":"Dumoulin",
    "gn:country_code":"GP",
    "gn:dem":34,
    "gn:feature_class":"P",
    "gn:feature_code":"PPL",
    "gn:name":"Dumoulin",
    "gn:population":0,
    "gn:timezone":"America/Guadeloupe",
    "iso:country":"GP",
    "name:fra_x_preferred":[
        "Dumoulin"
    ],
    "wof:name":"Dumoulin",
    "wof:placetype":"locality"
},
  "geometry": {"coordinates":[-61.49425,16.24888],"type":"Point"}
}