{
  "type": "Feature",
  "properties": {
    "gn:admin1_code":"00",
    "gn:asciiname":"Thomy",
    "gn:country_code":"GP",
    "gn:dem":195,
    "gn:feature_class":"P",
    "gn:feature_code":"PPL",
    "gn:name":"Thomy",
    "gn:population":0,
    "gn:timezone":"America/Guadeloupe",
    "iso:country":"GP",
    "name:fra_x_preferred":[
        "Thomy"
    ],
    "wof:name":"Thomy",
    "wof:placetype":"locality"
},
  "geometry": {"coordinates":[-61.77647,16.21913],"type":"Point"}
}