{
  "type": "Feature",
  "properties": {
    "gn:admin1_code":"00",
    "gn:asciiname":"Laurette",
    "gn:country_code":"GP",
    "gn:dem":7,
    "gn:feature_class":"P",
    "gn:feature_code":"PPL",
    "gn:name":"Laurette",
    "gn:population":0,
    "gn:timezone":"America/Guadeloupe",
    "iso:country":"GP",
    "name:fra_x_preferred":[
        "Laurette"
    ],
    "wof:name":"Laurette",
    "wof:placetype":"locality"
},
  "geometry": {"coordinates":[-61.64975,16.30595],"type":"Point"}
}