{
  "type": "Feature",
  "properties": {
    "gn:admin1_code":"00",
    "gn:asciiname":"Hanneton",
    "gn:country_code":"GP",
    "gn:dem":140,
    "gn:feature_class":"P",
    "gn:feature_code":"PPLL",
    "gn:name":"Hanneton",
    "gn:population":0,
    "gn:timezone":"America/Guadeloupe",
    "iso:country":"GP",
    "name:fra_x_preferred":[
        "Hanneton"
    ],
    "wof:name":"Hanneton",
    "wof:placetype":"locality"
},
  "geometry": {"coordinates":[-61.24456,15.88824],"type":"Point"}
}