{
  "type": "Feature",
  "properties": {
    "gn:admin1_code":"00",
    "gn:asciiname":"Guillon",
    "gn:country_code":"GP",
    "gn:dem":35,
    "gn:feature_class":"P",
    "gn:feature_code":"PPL",
    "gn:name":"Guillon",
    "gn:population":0,
    "gn:timezone":"America/Guadeloupe",
    "iso:country":"GP",
    "name:fra_x_preferred":[
        "Guillon"
    ],
    "wof:name":"Guillon",
    "wof:placetype":"locality"
},
  "geometry": {"coordinates":[-61.40794,16.22584],"type":"Point"}
}