{
  "type": "Feature",
  "properties": {
    "gn:admin1_code":"00",
    "gn:asciiname":"Poirier",
    "gn:country_code":"GP",
    "gn:dem":149,
    "gn:feature_class":"P",
    "gn:feature_code":"PPL",
    "gn:name":"Poirier",
    "gn:population":0,
    "gn:timezone":"America/Guadeloupe",
    "iso:country":"GP",
    "name:fra_x_preferred":[
        "Poirier"
    ],
    "wof:name":"Poirier",
    "wof:placetype":"locality"
},
  "geometry": {"coordinates":[-61.28816,15.95594],"type":"Point"}
}