{
  "type": "Feature",
  "properties": {
    "gn:admin1_code":"GP",
    "gn:admin2_code":"971",
    "gn:admin3_code":"9712.0",
    "gn:admin4_code":"97112.0",
    "gn:asciiname":"Bonneval",
    "gn:country_code":"GP",
    "gn:dem":13,
    "gn:feature_class":"P",
    "gn:feature_code":"PPL",
    "gn:name":"Bonneval",
    "gn:population":0,
    "gn:timezone":"America/Guadeloupe",
    "iso:country":"GP",
    "name:fra_x_preferred":[
        "Bonneval"
    ],
    "wof:name":"Bonneval",
    "wof:placetype":"locality"
},
  "geometry": {"coordinates":[-61.31916,15.8929],"type":"Point"}
}