{
  "type": "Feature",
  "properties": {
    "gn:admin1_code":"GP",
    "gn:admin2_code":"971",
    "gn:admin3_code":"9712.0",
    "gn:admin4_code":"97112.0",
    "gn:asciiname":"Bonneval",
    "gn:country_code":"GP",
    "gn:dem":13,
    "gn:feature_class":"P",
    "gn:feature_code":"PPL",
    "gn:name":"Bonneval",
    "gn:population":0,
    "gn:timezone":"America/Guadeloupe",
    "iso:country":"GP",
    "name:ceb_x_preferred":[
        "Bonneval"
    ],
    "name:deu_x_preferred":[
        "Bonneval"
    ],
    "name:fra_x_preferred":[
        "Bonneval"
    ],
    "name:ita_x_preferred":[
        "Bonneval"
    ],
    "name:nds_x_preferred":[
        "Bonneval"
    ],
    "name:nld_x_preferred":[
        "Bonneval"
    ],
    "name:oci_x_preferred":[
        "Bonneval"
    ],
    "name:pms_x_preferred":[
        "Bonneval"
    ],
    "name:pol_x_preferred":[
        "Bonneval"
    ],
    "name:por_x_preferred":[
        "Bonneval"
    ],
    "name:rus_x_preferred":[
        "\u0411\u043e\u043d\u0432\u0430\u043b\u044c"
    ],
    "name:sco_x_preferred":[
        "Bonneval"
    ],
    "name:slk_x_preferred":[
        "Bonneval"
    ],
    "name:spa_x_preferred":[
        "Bonneval"
    ],
    "name:srp_x_preferred":[
        "\u0411\u043e\u043d\u0432\u0430\u043b"
    ],
    "name:swe_x_preferred":[
        "Bonneval"
    ],
    "name:ukr_x_preferred":[
        "\u0411\u043e\u043d\u043d\u0432\u0430\u043b\u044c"
    ],
    "wof:name":"Bonneval",
    "wof:placetype":"locality"
},
  "geometry": {"coordinates":[-61.31916,15.8929],"type":"Point"}
}