{
  "type": "Feature",
  "properties": {
    "gn:admin1_code":"00",
    "gn:asciiname":"Sommabert",
    "gn:country_code":"GP",
    "gn:dem":58,
    "gn:feature_class":"P",
    "gn:feature_code":"PPL",
    "gn:name":"Sommabert",
    "gn:population":0,
    "gn:timezone":"America/Guadeloupe",
    "iso:country":"GP",
    "name:fra_x_preferred":[
        "Sommabert"
    ],
    "wof:name":"Sommabert",
    "wof:placetype":"locality"
},
  "geometry": {"coordinates":[-61.40263,16.34222999999999],"type":"Point"}
}