{
  "type": "Feature",
  "properties": {
    "gn:admin1_code":"GP",
    "gn:admin2_code":"971",
    "gn:admin3_code":"9711.0",
    "gn:admin4_code":"97115.0",
    "gn:asciiname":"Castel",
    "gn:country_code":"GP",
    "gn:dem":47,
    "gn:feature_class":"P",
    "gn:feature_code":"PPL",
    "gn:name":"Castel",
    "gn:population":0,
    "gn:timezone":"America/Guadeloupe",
    "iso:country":"GP",
    "name:fra_x_preferred":[
        "Castel"
    ],
    "wof:name":"Castel",
    "wof:placetype":"locality"
},
  "geometry": {"coordinates":[-61.66706,16.25893],"type":"Point"}
}