{
  "type": "Feature",
  "properties": {
    "gn:admin1_code":"00",
    "gn:asciiname":"La Treille",
    "gn:country_code":"GP",
    "gn:dem":94,
    "gn:feature_class":"P",
    "gn:feature_code":"PPL",
    "gn:name":"La Treille",
    "gn:population":0,
    "gn:timezone":"America/Guadeloupe",
    "iso:country":"GP",
    "name:fra_x_preferred":[
        "La Treille"
    ],
    "wof:name":"La Treille",
    "wof:placetype":"locality"
},
  "geometry": {"coordinates":[-61.30472,15.90018],"type":"Point"}
}