{
  "type": "Feature",
  "properties": {
    "gn:admin1_code":"00",
    "gn:asciiname":"Cima",
    "gn:country_code":"GP",
    "gn:dem":18,
    "gn:feature_class":"P",
    "gn:feature_code":"PPLL",
    "gn:name":"Cima",
    "gn:population":0,
    "gn:timezone":"America/Guadeloupe",
    "iso:country":"GP",
    "name:fra_x_preferred":[
        "Cima"
    ],
    "wof:name":"Cima",
    "wof:placetype":"locality"
},
  "geometry": {"coordinates":[-61.51213000000001,16.42044],"type":"Point"}
}