{
  "type": "Feature",
  "properties": {
    "gn:admin1_code":"00",
    "gn:asciiname":"Jabrun Saint-Cyr",
    "gn:country_code":"GP",
    "gn:dem":42,
    "gn:feature_class":"P",
    "gn:feature_code":"PPL",
    "gn:name":"Jabrun Saint-Cyr",
    "gn:population":0,
    "gn:timezone":"America/Guadeloupe",
    "iso:country":"GP",
    "name:fra_x_preferred":[
        "Jabrun Saint-Cyr"
    ],
    "wof:name":"Jabrun Saint-Cyr",
    "wof:placetype":"locality"
},
  "geometry": {"coordinates":[-61.44416999999999,16.31594],"type":"Point"}
}