{
  "type": "Feature",
  "properties": {
    "gn:admin1_code":"GP",
    "gn:admin2_code":"971",
    "gn:admin3_code":"9712.0",
    "gn:admin4_code":"97128.0",
    "gn:asciiname":"Belle Place",
    "gn:country_code":"GP",
    "gn:dem":116,
    "gn:feature_class":"P",
    "gn:feature_code":"PPL",
    "gn:name":"Belle Place",
    "gn:population":0,
    "gn:timezone":"America/Guadeloupe",
    "iso:country":"GP",
    "name:fra_x_preferred":[
        "Belle Place"
    ],
    "wof:name":"Belle Place",
    "wof:placetype":"locality"
},
  "geometry": {"coordinates":[-61.43646999999999,16.26676],"type":"Point"}
}