{
  "type": "Feature",
  "properties": {
    "gn:admin1_code":"00",
    "gn:asciiname":"Maillard",
    "gn:country_code":"GP",
    "gn:dem":45,
    "gn:feature_class":"P",
    "gn:feature_code":"PPL",
    "gn:name":"Maillard",
    "gn:population":0,
    "gn:timezone":"America/Guadeloupe",
    "iso:country":"GP",
    "name:cat_x_preferred":[
        "Maillard"
    ],
    "name:deu_x_preferred":[
        "Maillard"
    ],
    "name:fra_x_preferred":[
        "Maillard"
    ],
    "name:ita_x_preferred":[
        "Maillard"
    ],
    "name:nds_x_preferred":[
        "Maillard"
    ],
    "name:nld_x_preferred":[
        "Maillard"
    ],
    "name:por_x_preferred":[
        "Maillard"
    ],
    "name:rus_x_preferred":[
        "\u041c\u0430\u0439\u044f\u0440"
    ],
    "wof:name":"Maillard",
    "wof:placetype":"locality"
},
  "geometry": {"coordinates":[-61.23575,15.88371],"type":"Point"}
}