{
  "type": "Feature",
  "properties": {
    "gn:admin1_code":"GP",
    "gn:admin2_code":"971",
    "gn:admin3_code":"9712.0",
    "gn:admin4_code":"97119.0",
    "gn:asciiname":"Gros Cap",
    "gn:country_code":"GP",
    "gn:dem":54,
    "gn:feature_class":"P",
    "gn:feature_code":"PPL",
    "gn:name":"Gros Cap",
    "gn:population":0,
    "gn:timezone":"America/Guadeloupe",
    "iso:country":"GP",
    "name:fra_x_preferred":[
        "Gros Cap"
    ],
    "wof:name":"Gros Cap",
    "wof:placetype":"locality"
},
  "geometry": {"coordinates":[-61.41812,16.40597],"type":"Point"}
}