{
  "type": "Feature",
  "properties": {
    "gn:admin1_code":"GP",
    "gn:admin2_code":"971",
    "gn:admin3_code":"9712.0",
    "gn:admin4_code":"97113.0",
    "gn:asciiname":"Port Blanc",
    "gn:country_code":"GP",
    "gn:dem":83,
    "gn:feature_class":"P",
    "gn:feature_code":"PPL",
    "gn:name":"Port Blanc",
    "gn:population":0,
    "gn:timezone":"America/Guadeloupe",
    "iso:country":"GP",
    "name:fra_x_preferred":[
        "Port Blanc"
    ],
    "wof:name":"Port Blanc",
    "wof:placetype":"locality"
},
  "geometry": {"coordinates":[-61.45615,16.23335],"type":"Point"}
}