{
  "type": "Feature",
  "properties": {
    "gn:admin1_code":"GP",
    "gn:admin2_code":"971",
    "gn:admin3_code":"9712.0",
    "gn:admin4_code":"97126.0",
    "gn:asciiname":"Pelisson",
    "gn:country_code":"GP",
    "gn:dem":126,
    "gn:feature_class":"P",
    "gn:feature_code":"PPL",
    "gn:name":"P\u00e9lisson",
    "gn:population":0,
    "gn:timezone":"America/Guadeloupe",
    "iso:country":"GP",
    "name:fra_x_preferred":[
        "P\u00e9lisson"
    ],
    "wof:name":"Pelisson",
    "wof:placetype":"locality"
},
  "geometry": {"coordinates":[-61.26833000000001,15.93301],"type":"Point"}
}