{
  "type": "Feature",
  "properties": {
    "gn:admin1_code":"GP",
    "gn:admin2_code":"971",
    "gn:admin3_code":"9712.0",
    "gn:admin4_code":"97112.0",
    "gn:asciiname":"Lami",
    "gn:country_code":"GP",
    "gn:dem":28,
    "gn:feature_class":"P",
    "gn:feature_code":"PPL",
    "gn:name":"Lami",
    "gn:population":0,
    "gn:timezone":"America/Guadeloupe",
    "iso:country":"GP",
    "name:fra_x_preferred":[
        "Lami"
    ],
    "wof:name":"Lami",
    "wof:placetype":"locality"
},
  "geometry": {"coordinates":[-61.31179,15.8925],"type":"Point"}
}