{
  "type": "Feature",
  "properties": {
    "gn:admin1_code":"00",
    "gn:asciiname":"La Haut",
    "gn:country_code":"GP",
    "gn:dem":164,
    "gn:feature_class":"P",
    "gn:feature_code":"PPL",
    "gn:name":"La Haut",
    "gn:population":0,
    "gn:timezone":"America/Guadeloupe",
    "iso:country":"GP",
    "name:fra_x_preferred":[
        "La Haut"
    ],
    "wof:name":"La Haut",
    "wof:placetype":"locality"
},
  "geometry": {"coordinates":[-61.24681,15.9534],"type":"Point"}
}