{
  "type": "Feature",
  "properties": {
    "gn:admin1_code":"00",
    "gn:asciiname":"Despont",
    "gn:country_code":"GP",
    "gn:dem":110,
    "gn:feature_class":"P",
    "gn:feature_code":"PPL",
    "gn:name":"Despont",
    "gn:population":0,
    "gn:timezone":"America/Guadeloupe",
    "iso:country":"GP",
    "name:fra_x_preferred":[
        "Despont"
    ],
    "wof:name":"Despont",
    "wof:placetype":"locality"
},
  "geometry": {"coordinates":[-61.75183000000001,16.06942],"type":"Point"}
}