{
  "type": "Feature",
  "properties": {
    "gn:admin1_code":"00",
    "gn:asciiname":"Rejoui",
    "gn:country_code":"GP",
    "gn:dem":54,
    "gn:feature_class":"P",
    "gn:feature_code":"PPLL",
    "gn:name":"R\u00e9joui",
    "gn:population":0,
    "gn:timezone":"America/Guadeloupe",
    "iso:country":"GP",
    "name:fra_x_preferred":[
        "R\u00e9joui"
    ],
    "wof:name":"Rejoui",
    "wof:placetype":"locality"
},
  "geometry": {"coordinates":[-61.5028,16.23329],"type":"Point"}
}