{
  "type": "Feature",
  "properties": {
    "gn:admin1_code":"GP",
    "gn:admin2_code":"971",
    "gn:admin3_code":"9712.0",
    "gn:admin4_code":"97112.0",
    "gn:asciiname":"Saint-Charles",
    "gn:country_code":"GP",
    "gn:dem":18,
    "gn:feature_class":"P",
    "gn:feature_code":"PPL",
    "gn:name":"Saint-Charles",
    "gn:population":0,
    "gn:timezone":"America/Guadeloupe",
    "iso:country":"GP",
    "name:fra_x_preferred":[
        "Saint-Charles"
    ],
    "wof:name":"Saint-Charles",
    "wof:placetype":"locality"
},
  "geometry": {"coordinates":[-61.30765,15.94156],"type":"Point"}
}