{
  "type": "Feature",
  "properties": {
    "gn:admin1_code":"GP",
    "gn:admin2_code":"971",
    "gn:admin3_code":"9712.0",
    "gn:admin4_code":"97128.0",
    "gn:asciiname":"Berard",
    "gn:country_code":"GP",
    "gn:dem":34,
    "gn:feature_class":"P",
    "gn:feature_code":"PPL",
    "gn:name":"B\u00e9rard",
    "gn:population":0,
    "gn:timezone":"America/Guadeloupe",
    "iso:country":"GP",
    "name:und_x_variant":[
        "De B\u00e9rard",
        "B\u00e9rard"
    ],
    "wof:name":"Berard",
    "wof:placetype":"locality"
},
  "geometry": {"coordinates":[-61.35625,16.25875],"type":"Point"}
}