{
  "type": "Feature",
  "properties": {
    "gn:admin1_code":"00",
    "gn:asciiname":"D'Arles",
    "gn:country_code":"GP",
    "gn:dem":30,
    "gn:feature_class":"P",
    "gn:feature_code":"PPLL",
    "gn:name":"D\u2019Arles",
    "gn:population":0,
    "gn:timezone":"America/Guadeloupe",
    "iso:country":"GP",
    "name:fra_x_preferred":[
        "D\u2019Arles"
    ],
    "wof:name":"D'Arles",
    "wof:placetype":"locality"
},
  "geometry": {"coordinates":[-61.32100000000001,16.31752],"type":"Point"}
}