{
  "type": "Feature",
  "properties": {
    "gn:admin1_code":"00",
    "gn:asciiname":"Cafeiere",
    "gn:country_code":"GP",
    "gn:dem":23,
    "gn:feature_class":"P",
    "gn:feature_code":"PPL",
    "gn:name":"Caf\u00e9i\u00e8re",
    "gn:population":0,
    "gn:timezone":"America/Guadeloupe",
    "iso:country":"GP",
    "name:fra_x_preferred":[
        "Caf\u00e9i\u00e8re"
    ],
    "wof:name":"Cafeiere",
    "wof:placetype":"locality"
},
  "geometry": {"coordinates":[-61.38104000000001,16.30468],"type":"Point"}
}