{
  "type": "Feature",
  "properties": {
    "gn:admin1_code":"GP",
    "gn:admin2_code":"971",
    "gn:admin3_code":"9711.0",
    "gn:admin4_code":"97107.0",
    "gn:asciiname":"Routhiers",
    "gn:country_code":"GP",
    "gn:dem":183,
    "gn:feature_class":"P",
    "gn:feature_code":"PPL",
    "gn:name":"Routhiers",
    "gn:population":0,
    "gn:timezone":"America/Guadeloupe",
    "iso:country":"GP",
    "name:fra_x_preferred":[
        "Routhiers"
    ],
    "wof:name":"Routhiers",
    "wof:placetype":"locality"
},
  "geometry": {"coordinates":[-61.59726,16.04041],"type":"Point"}
}