{
  "type": "Feature",
  "properties": {
    "gn:admin1_code":"00",
    "gn:asciiname":"Pierre Claire",
    "gn:country_code":"GP",
    "gn:dem":50,
    "gn:feature_class":"P",
    "gn:feature_code":"PPL",
    "gn:name":"Pierre Claire",
    "gn:population":0,
    "gn:timezone":"America/Guadeloupe",
    "iso:country":"GP",
    "name:fra_x_preferred":[
        "Pierre Claire"
    ],
    "wof:name":"Pierre Claire",
    "wof:placetype":"locality"
},
  "geometry": {"coordinates":[-61.22445,15.89354],"type":"Point"}
}