{
  "type": "Feature",
  "properties": {
    "gn:admin1_code":"GP",
    "gn:admin2_code":"971",
    "gn:admin3_code":"9711.0",
    "gn:admin4_code":"97134.0",
    "gn:asciiname":"Bichemin",
    "gn:country_code":"GP",
    "gn:dem":209,
    "gn:feature_class":"P",
    "gn:feature_code":"PPL",
    "gn:name":"Bichemin",
    "gn:population":0,
    "gn:timezone":"America/Guadeloupe",
    "iso:country":"GP",
    "name:fra_x_preferred":[
        "Bichemin"
    ],
    "wof:name":"Bichemin",
    "wof:placetype":"locality"
},
  "geometry": {"coordinates":[-61.74406,16.07721],"type":"Point"}
}