{
  "type": "Feature",
  "properties": {
    "gn:admin1_code":"00",
    "gn:asciiname":"Fond Boucard",
    "gn:country_code":"GP",
    "gn:dem":37,
    "gn:feature_class":"P",
    "gn:feature_code":"PPLL",
    "gn:name":"Fond Boucard",
    "gn:population":0,
    "gn:timezone":"America/Guadeloupe",
    "iso:country":"GP",
    "name:fra_x_preferred":[
        "Fond Boucard"
    ],
    "wof:name":"Fond Boucard",
    "wof:placetype":"locality"
},
  "geometry": {"coordinates":[-61.43183000000001,16.34899],"type":"Point"}
}