{
  "type": "Feature",
  "properties": {
    "gn:admin1_code":"00",
    "gn:asciiname":"Sainte-Elise",
    "gn:country_code":"GP",
    "gn:dem":43,
    "gn:feature_class":"P",
    "gn:feature_code":"PPL",
    "gn:name":"Sainte-\u00c9lise",
    "gn:population":0,
    "gn:timezone":"America/Guadeloupe",
    "iso:country":"GP",
    "name:fra_x_preferred":[
        "Sainte-\u00c9lise"
    ],
    "wof:name":"Sainte-Elise",
    "wof:placetype":"locality"
},
  "geometry": {"coordinates":[-61.70132,16.32767999999999],"type":"Point"}
}