{
  "type": "Feature",
  "properties": {
    "gn:admin1_code":"00",
    "gn:asciiname":"Carriere",
    "gn:country_code":"GP",
    "gn:dem":34,
    "gn:feature_class":"P",
    "gn:feature_code":"PPL",
    "gn:name":"Carri\u00e8re",
    "gn:population":0,
    "gn:timezone":"America/Guadeloupe",
    "iso:country":"GP",
    "name:fra_x_preferred":[
        "Carri\u00e8re"
    ],
    "wof:name":"Carriere",
    "wof:placetype":"locality"
},
  "geometry": {"coordinates":[-61.40886999999999,16.21491],"type":"Point"}
}