{
  "type": "Feature",
  "properties": {
    "gn:admin1_code":"GP",
    "gn:admin2_code":"971",
    "gn:admin3_code":"9712.0",
    "gn:admin4_code":"97125.0",
    "gn:asciiname":"Guyot",
    "gn:country_code":"GP",
    "gn:dem":46,
    "gn:feature_class":"P",
    "gn:feature_code":"PPL",
    "gn:name":"Guyot",
    "gn:population":0,
    "gn:timezone":"America/Guadeloupe",
    "iso:country":"GP",
    "name:ara_x_preferred":[
        "\u062c\u064a\u0648\u062a"
    ],
    "name:ast_x_preferred":[
        "Guyot"
    ],
    "name:cat_x_preferred":[
        "Guyot"
    ],
    "name:ces_x_preferred":[
        "Guyot"
    ],
    "name:deu_x_preferred":[
        "Guyot"
    ],
    "name:epo_x_preferred":[
        "Gujoto"
    ],
    "name:est_x_preferred":[
        "Gaiot"
    ],
    "name:eus_x_preferred":[
        "Guiot"
    ],
    "name:fas_x_preferred":[
        "\u0641\u06cc\u0646\u0647"
    ],
    "name:fra_x_preferred":[
        "Guyot"
    ],
    "name:glg_x_preferred":[
        "Guyot"
    ],
    "name:ita_x_preferred":[
        "Guyot"
    ],
    "name:jpn_x_preferred":[
        "\u30ae\u30e8\u30fc"
    ],
    "name:kaz_x_preferred":[
        "\u0413\u0430\u0439\u043e\u0442"
    ],
    "name:kor_x_preferred":[
        "\ud3c9\uc815\ud574\uc0b0"
    ],
    "name:lit_x_preferred":[
        "Gajotas"
    ],
    "name:nld_x_preferred":[
        "Guyot"
    ],
    "name:nno_x_preferred":[
        "Guyot"
    ],
    "name:nor_x_preferred":[
        "Guyot"
    ],
    "name:pol_x_preferred":[
        "Gujot"
    ],
    "name:por_x_preferred":[
        "Guyot"
    ],
    "name:rus_x_preferred":[
        "\u0413\u0430\u0439\u043e\u0442"
    ],
    "name:spa_x_preferred":[
        "Guyot"
    ],
    "name:swe_x_preferred":[
        "Guyot"
    ],
    "name:tha_x_preferred":[
        "\u0e40\u0e02\u0e32\u0e22\u0e2d\u0e14\u0e23\u0e32\u0e1a\u0e43\u0e15\u0e49\u0e2a\u0e21\u0e38\u0e17\u0e23"
    ],
    "name:tur_x_preferred":[
        "Guyot"
    ],
    "name:ukr_x_preferred":[
        "\u0413\u0430\u0439\u043e\u0442"
    ],
    "name:und_x_variant":[
        "Guillot"
    ],
    "name:war_x_preferred":[
        "Guyot"
    ],
    "name:zho_x_preferred":[
        "\u6d77\u5e95\u5e73\u9802\u5c71"
    ],
    "wof:name":"Guyot",
    "wof:placetype":"locality"
},
  "geometry": {"coordinates":[-61.26869,16.28743],"type":"Point"}
}