{
  "type": "Feature",
  "properties": {
    "gn:admin1_code":"GP",
    "gn:admin2_code":"971",
    "gn:admin3_code":"9712.0",
    "gn:admin4_code":"97125.0",
    "gn:asciiname":"Guyot",
    "gn:country_code":"GP",
    "gn:dem":46,
    "gn:feature_class":"P",
    "gn:feature_code":"PPL",
    "gn:name":"Guyot",
    "gn:population":0,
    "gn:timezone":"America/Guadeloupe",
    "iso:country":"GP",
    "name:fra_x_preferred":[
        "Guyot"
    ],
    "name:und_x_variant":[
        "Guillot"
    ],
    "wof:name":"Guyot",
    "wof:placetype":"locality"
},
  "geometry": {"coordinates":[-61.26869,16.28743],"type":"Point"}
}